{
    "1099500": {
        "deprecated": false,
        "Dev_Desc": "해수 퀘스트 메인 NPC",
        "id": 1099500,
        "alias": "Contents.Citizen.Name.199500",
        "text": "추수갓"
    },
    "1099501": {
        "deprecated": false,
        "Dev_Desc": "해수 퀘스트 서브 NPC 1",
        "id": 1099501,
        "alias": "Contents.Citizen.Name.199501",
        "text": "오도독"
    },
    "1099502": {
        "deprecated": false,
        "Dev_Desc": "해수 퀘스트 서브 NPC 2",
        "id": 1099502,
        "alias": "Contents.Citizen.Name.199502",
        "text": "우두둑"
    },
    "1099503": {
        "deprecated": false,
        "Dev_Desc": "해수 퀘스트 서브 NPC 3",
        "id": 1099503,
        "alias": "Contents.Citizen.Name.199503",
        "text": "우지근"
    }
}