{
    "99000865": {
        "deprecated": false,
        "Dev_Desc": "일반 / 막기 / 특화무공 (각인)",
        "id": 99000865,
        "alias": "Contents.Item.Desc.9100110",
        "text": "Guards attack from the front."
    },
    "99000866": {
        "deprecated": false,
        "Dev_Desc": "일반 / 찔러베기 / 액티브 (각인)",
        "id": 99000866,
        "alias": "Contents.Item.Desc.9100111",
        "text": "Quickly stabs and slashes to deal multiple attacks."
    },
    "99000867": {
        "deprecated": false,
        "Dev_Desc": "일반 / 찌르기 / 액티브 (각인)",
        "id": 99000867,
        "alias": "Contents.Item.Desc.9100112",
        "text": "Stabs an enemy to deal damage.\nCan be used in a combo attack after an attack skill."
    },
    "99000868": {
        "deprecated": false,
        "Dev_Desc": "일반 / 악력운동 / 패시브 (각인)",
        "id": 99000868,
        "alias": "Contents.Item.Desc.9100113",
        "text": "Exercises to strengthen the sword grip.\nIncreases Sword Attack."
    },
    "99000869": {
        "deprecated": false,
        "Dev_Desc": "반격찌르기 / 일반 검 무공서 (각인)",
        "id": 99000869,
        "alias": "Contents.Item.Desc.9100114",
        "text": "Removes the block and performs a long-range stab attack. Can be used when the soul parry is successful."
    },
    "99000875": {
        "deprecated": false,
        "Dev_Desc": "상급 / 올려베기 / 액티브 / 각인",
        "id": 99000875,
        "alias": "Contents.Item.Desc.9100120",
        "text": "Slashes upward to deal damage\nHas a chance to send the enemy airborne.\nInflicts Stun on impact with the ground."
    },
    "99000876": {
        "deprecated": false,
        "Dev_Desc": "상급 / 뛰어베기 / 액티브 / 각인",
        "id": 99000876,
        "alias": "Contents.Item.Desc.9100121",
        "text": "Dashes forward and deals powerful damage.\nHas a chance to inflict Petrify."
    },
    "99000877": {
        "deprecated": false,
        "Dev_Desc": "상급 / 몸풀기 / 패시브 / 각인",
        "id": 99000877,
        "alias": "Contents.Item.Desc.9100122",
        "text": "Warms up the body to increase flexibility.\nIncreases Normal Attack Speed and Move Speed Rate."
    },
    "99000878": {
        "deprecated": false,
        "Dev_Desc": "상급 / 근력운동 / 패시브 / 각인",
        "id": 99000878,
        "alias": "Contents.Item.Desc.9100123",
        "text": "Consistently performs high-intensity muscle training.\nIncreases STR."
    },
    "99000879": {
        "deprecated": false,
        "Dev_Desc": "발도 / 상급 검 무공서 (각인)",
        "id": 99000879,
        "alias": "Contents.Item.Desc.9100124",
        "text": "Attacks a foot that can attack in quick succession.\\nUsed on targets that are in stun or air status."
    },
    "99000885": {
        "deprecated": false,
        "Dev_Desc": "희귀 / 천지가르기 / 액티브 / 각인",
        "id": 99000885,
        "alias": "Contents.Item.Desc.9100130",
        "text": "Deals powerful damage by striking down an enemy with full force using a sword.\nCan be used on an airborne and stunned enemy.\nCan be used in combo with Airborne and Stun."
    },
    "99000886": {
        "deprecated": false,
        "Dev_Desc": "일반 / 일섬 / 특화 / 각인",
        "id": 99000886,
        "alias": "Contents.Item.Desc.9100131",
        "text": "Dashes forward and attacks 2 times in a row.\nDeals damage and has a chance to inflict Petrify."
    },
    "99000887": {
        "deprecated": false,
        "Dev_Desc": "희귀 / 흔들기 / 패시브 / 각인",
        "id": 99000887,
        "alias": "Contents.Item.Desc.9100132",
        "text": "Throws off enemy's balance.\nIncrease CC Accuracy."
    },
    "99000888": {
        "deprecated": false,
        "Dev_Desc": "희귀 / 검날손질 / 패시브 / 각인",
        "id": 99000888,
        "alias": "Contents.Item.Desc.9100133",
        "text": "Sharpens the blade.\nIncreases Melee Piercing Damage."
    },
    "99000895": {
        "deprecated": false,
        "Dev_Desc": "영웅 / 어검징표 / 액티브 / 각인",
        "id": 99000895,
        "alias": "Contents.Item.Desc.9100140",
        "text": "Stabs enemy with Spectral Blade to deal damage.\nDeals damage and inflicts Soul Stab.\nIncreases received damage while casting Soul Stab."
    },
    "99000896": {
        "deprecated": false,
        "Dev_Desc": "전설 / 하늘베기 / 액티브 / 각인",
        "id": 99000896,
        "alias": "Contents.Item.Desc.9100141",
        "text": "Approaches to deal a powerful multi attack.\nDeals damage and has a chance to inflict Airborne.\nInflicts Stun on impact with the ground.\nHas a higher Accuracy chance on an enemy afflicted with Soul Stab."
    },
    "99000897": {
        "deprecated": false,
        "Dev_Desc": "영웅 / 신검합일 / 패시브 / 각인",
        "id": 99000897,
        "alias": "Contents.Item.Desc.9100142",
        "text": "Boosts Attack ability by uniting with the sword.\nIncreases Amplified Weapon Attack and Precision."
    },
    "99000898": {
        "deprecated": false,
        "Dev_Desc": "영웅 / 휘몰아치기 / 패시브",
        "id": 99000898,
        "alias": "Contents.Item.Desc.9100143",
        "text": "Raises the momentum to drive the attack.\\nWhen hit with no attack, there is a chance to gain the effect of Sweeping for 10 seconds.\\nIncreasing attack speed during Sweeping.\\nStacks up to 5 times."
    },
    "99000899": {
        "deprecated": false,
        "Dev_Desc": "검술연계Ⅰ",
        "id": 99000899,
        "alias": "Contents.Item.Desc.9100144",
        "text": "보스 몬스터 공격 시 일정 확률로 \"천지가르기\", \"구름베기\"가 활성화됩니다.\n(사용 무공 활성화 대기시간 15초)"
    },
    "99000905": {
        "deprecated": false,
        "Dev_Desc": "전설 / 약점공략 / 패시브 / 각인",
        "id": 99000905,
        "alias": "Contents.Item.Desc.9100150",
        "text": "The blade pinpoints the weak spot.\nIncreases Melee Attack."
    },
    "99000906": {
        "deprecated": false,
        "Dev_Desc": "영웅 / 번개베기 / 무기스킬 / 각인",
        "id": 99000906,
        "alias": "Contents.Item.Desc.9100151",
        "text": "Deals powerful damage.\nHas a chance to inflict Stun."
    },
    "99000907": {
        "deprecated": false,
        "Dev_Desc": "영웅 / 구름베기 / 무기스킬 / 각인",
        "id": 99000907,
        "alias": "Contents.Item.Desc.9100152",
        "text": "Deals damage and has a chance to inflict Airborne.\nInflicts Stun on impact with the ground.\nCan be used on an airborne and stunned enemy.\nCan be used in combo with Airborne and Stun."
    },
    "99000916": {
        "deprecated": false,
        "Dev_Desc": "일반 / 횡이동 / 특화 / 각인",
        "id": 99000916,
        "alias": "Contents.Item.Desc.9100210",
        "text": "Swiftly moves to the rear of the target."
    },
    "99000917": {
        "deprecated": false,
        "Dev_Desc": "일반 / 회천각 / 액티브 / 각인",
        "id": 99000917,
        "alias": "Contents.Item.Desc.9100211",
        "text": "Deals damage to an enemy by launching a wide kick."
    },
    "99000918": {
        "deprecated": false,
        "Dev_Desc": "일반 / 승룡각 / 액티브 / 각인",
        "id": 99000918,
        "alias": "Contents.Item.Desc.9100212",
        "text": "Spins feet in the air to deal damage.\nCan move while casting this technique."
    },
    "99000919": {
        "deprecated": false,
        "Dev_Desc": "일반 / 집중 / 패시브 / 각인",
        "id": 99000919,
        "alias": "Contents.Item.Desc.9100213",
        "text": "Slightly increases Attack Speed through concentration.\nIncreases Normal Attack Speed."
    },
    "99000920": {
        "deprecated": false,
        "Dev_Desc": "일반 / 파쇄격 / EQ",
        "id": 99000920,
        "alias": "Contents.Item.Desc.9100214"
    },
    "99000926": {
        "deprecated": false,
        "Dev_Desc": "상급 / 절명각 / 액티브 / 각인",
        "id": 99000926,
        "alias": "Contents.Item.Desc.9100220",
        "text": "Makes a short dash toward the enemy and sweeps with a leg to deal damage."
    },
    "99000927": {
        "deprecated": false,
        "Dev_Desc": "상급 / 비염각 / 액티브 / 각인",
        "id": 99000927,
        "alias": "Contents.Item.Desc.9100221",
        "text": "Flies toward enemy, kicks to deal damage, and has a chance to inflict Petrify."
    },
    "99000928": {
        "deprecated": false,
        "Dev_Desc": "상급 / 근력 / 패시브 / 각인",
        "id": 99000928,
        "alias": "Contents.Item.Desc.9100222",
        "text": "Trains muscles to boost the weapon's destructive power.\nIncreases Gauntlets Attack."
    },
    "99000929": {
        "deprecated": false,
        "Dev_Desc": "상급 / 강기 / 패시브 / 각인",
        "id": 99000929,
        "alias": "Contents.Item.Desc.9100223",
        "text": "Learns how to control chi.\nIncreases STR and CON."
    },
    "99000930": {
        "deprecated": false,
        "Dev_Desc": "상급 / 연권 / QQ",
        "id": 99000930,
        "alias": "Contents.Item.Desc.9100224",
        "text": "대상에게 좌우로 주먹을 빠르게 날립니다.\n소울 패링 기절 대상에게 공격 버튼을 수동으로 눌러 사용 가능합니다."
    },
    "99000936": {
        "deprecated": false,
        "Dev_Desc": "희귀 / 다리걸기 / 액티브 / 각인",
        "id": 99000936,
        "alias": "Contents.Item.Desc.9100230",
        "text": "Has a chance to stun the enemy by tripping them."
    },
    "99000937": {
        "deprecated": false,
        "Dev_Desc": "영웅 / 연권 / 액티브 / 각인",
        "id": 99000937,
        "alias": "Contents.Item.Desc.9100231",
        "text": "Dashes toward enemy to rapidly hit them, inflicting Petrify and dealing damage.\nThe last hit shoves the enemy to inflict Stun."
    },
    "99000939": {
        "deprecated": false,
        "Dev_Desc": "희귀 / 날렵함 / 패시브 / 각인",
        "id": 99000939,
        "alias": "Contents.Item.Desc.9100233",
        "text": "Lightens the body.\nIncrease Evasion and Move Speed."
    },
    "99000940": {
        "deprecated": false,
        "Dev_Desc": "희귀 / 맹호격 / 액티브 / 각인",
        "id": 99000940,
        "alias": "Contents.Item.Desc.9100234",
        "text": "Leaps into the air and smashes the ground. Has a chance to stun and deal damage to enemy."
    },
    "99000946": {
        "deprecated": false,
        "Dev_Desc": "영웅 / 붕권 / 액티브 / 각인",
        "id": 99000946,
        "alias": "Contents.Item.Desc.9100240",
        "text": "Throws a fist at a single enemy, forces the enemy back to deal damage and has a chance to inflict Stun.\nHas a chance to pierce the target's block and inflict Stun."
    },
    "99000947": {
        "deprecated": false,
        "Dev_Desc": "희귀 / 승천권 / 액티브 / 각인",
        "id": 99000947,
        "alias": "Contents.Item.Desc.9100241",
        "text": "Makes a short dash toward an enemy. Has a chance to inflict Airborne."
    },
    "99000948": {
        "deprecated": false,
        "Dev_Desc": "영웅 / 뇌진탕 / 패시브 / 각인",
        "id": 99000948,
        "alias": "Contents.Item.Desc.9100242",
        "text": "Has a chance to petrify the enemy upon landing a normal attack."
    },
    "99000949": {
        "deprecated": false,
        "Dev_Desc": "희귀 / 무투 / 패시브 / 각인",
        "id": 99000949,
        "alias": "Contents.Item.Desc.9100243",
        "text": "Deals more damage with normal attack on enemy afflicted with CC.\nIncreases Normal Attack Damage."
    },
    "99000950": {
        "deprecated": false,
        "Dev_Desc": "영웅 / 강격 / 패시브 / 각인",
        "id": 99000950,
        "alias": "Contents.Item.Desc.9100244",
        "text": "Gains confidence by surpassing the limits.\nIncreases Block Piercing."
    },
    "99000951": {
        "deprecated": false,
        "Dev_Desc": "개혈 / 액티브",
        "id": 99000951,
        "alias": "Contents.Item.Desc.9100245",
        "text": "혈도를 개방시켜 6초간 근거리 공격력이 증가하고 대상에게 공격 적중 시 일정 확률로 생명력을 회복합니다."
    },
    "99000952": {
        "deprecated": false,
        "Dev_Desc": "영웅 / 권법연계Ⅰ / 패시브 / 각인",
        "id": 99000952,
        "alias": "Contents.Item.Desc.9100246",
        "text": "보스 몬스터 공격 시 일정 확률로 \"절명각\", \"맹호격\", \"승천권\"이 활성화됩니다.\n(사용 무공 활성화 대기시간 15초)"
    },
    "99000956": {
        "deprecated": false,
        "Dev_Desc": "전설 / 초월권무 / 액티브 / 각인",
        "id": 99000956,
        "alias": "Contents.Item.Desc.9100250",
        "text": "Dashes toward an enemy and uses powerful combo attacks.\nThe last blow has a chance to push and stun the enemy.\nThe caster is immune to all damage while using the technique."
    },
    "99000957": {
        "deprecated": false,
        "Dev_Desc": "전설 / 개혈 / 패시브 / 각인",
        "id": 99000957,
        "alias": "Contents.Item.Desc.9100251",
        "text": "Accelerates metabolism by unleashing vital points.\nIncreases Soul Chance."
    },
    "99000958": {
        "deprecated": false,
        "Dev_Desc": "전설 / 급소가격 / 패시브 / 각인",
        "id": 99000958,
        "alias": "Contents.Item.Desc.9100252",
        "text": "Has a chance to stun the enemy upon landing a normal attack."
    },
    "99000967": {
        "deprecated": false,
        "Dev_Desc": "증폭의 정수 : 찔러베기 (각인)",
        "id": 99000967,
        "alias": "Contents.Item.Desc.9101110",
        "text": "Used to level up Dashing Slash.\nIncreases its damage."
    },
    "99000968": {
        "deprecated": false,
        "Dev_Desc": "증폭의 정수 : 찌르기 (각인)",
        "id": 99000968,
        "alias": "Contents.Item.Desc.9101111",
        "text": "Used to level up Stab.\nDecreases its Focus cost."
    },
    "99000969": {
        "deprecated": false,
        "Dev_Desc": "증폭의 정수 : 일섬 (각인)",
        "id": 99000969,
        "alias": "Contents.Item.Desc.9101112",
        "text": "Used to level up Block.\nIncreases Melee Accuracy upon successful Block."
    },
    "99000977": {
        "deprecated": false,
        "Dev_Desc": "극한의 정수 : 찔러베기 (각인)",
        "id": 99000977,
        "alias": "Contents.Item.Desc.9101120",
        "text": "Used to level up Dashing Slash.\nDecreases its cooldown."
    },
    "99000978": {
        "deprecated": false,
        "Dev_Desc": "극한의 정수 : 찌르기 (각인)",
        "id": 99000978,
        "alias": "Contents.Item.Desc.9101121",
        "text": "Used to level up Stab.\nStabs 2 times."
    },
    "99000979": {
        "deprecated": false,
        "Dev_Desc": "증폭의 정수 : 뛰어베기 (각인)",
        "id": 99000979,
        "alias": "Contents.Item.Desc.9101122",
        "text": "Used to level up Jumping Slash.\nDecreases its Focus cost."
    },
    "99000980": {
        "deprecated": false,
        "Dev_Desc": "증폭의 정수 : 올려베기 (각인)",
        "id": 99000980,
        "alias": "Contents.Item.Desc.9101123",
        "text": "Used to level up Upward Thrust.\nDecreases its cooldown."
    },
    "99000987": {
        "deprecated": false,
        "Dev_Desc": "돌파의 정수 : 찔러베기 (각인)",
        "id": 99000987,
        "alias": "Contents.Item.Desc.9101130",
        "text": "Used to level up Dashing Slash.\nDecreases its Focus cost."
    },
    "99000988": {
        "deprecated": false,
        "Dev_Desc": "돌파의 정수 : 찌르기 (각인)",
        "id": 99000988,
        "alias": "Contents.Item.Desc.9101131",
        "text": "Used to level up Stab.\nStabs 3 times."
    },
    "99000989": {
        "deprecated": false,
        "Dev_Desc": "극한의 정수 : 막기 (각인)",
        "id": 99000989,
        "alias": "Contents.Item.Desc.9101132",
        "text": "Used to level up Block.\nIncreases the duration of Defense."
    },
    "99000990": {
        "deprecated": false,
        "Dev_Desc": "극한의 정수 : 올려베기 (각인)",
        "id": 99000990,
        "alias": "Contents.Item.Desc.9101133",
        "text": "Used to level up Upward Thrust.\nDeals an extra attack to the airborne enemy."
    },
    "99000991": {
        "deprecated": false,
        "Dev_Desc": "극한의 정수 : 뛰어베기 (각인)",
        "id": 99000991,
        "alias": "Contents.Item.Desc.9101134",
        "text": "Used to level up Jumping Slash.\nIncreases its damage."
    },
    "99000992": {
        "deprecated": false,
        "Dev_Desc": "돌파의 정수 : 천지가르기",
        "id": 99000992,
        "alias": "Contents.Item.Desc.9101135",
        "text": "Essence used for the evolution of Thunderstruck. \\n Performs additional combo attacks when evolving."
    },
    "99000993": {
        "deprecated": false,
        "Dev_Desc": "돌파의 정수 : 일섬 ",
        "id": 99000993,
        "alias": "Contents.Item.Desc.9101136",
        "text": "Essence used for the evolution of one island.\\nWhen evolving, the distance and damage used by the target of Sword Sword Mark increases."
    },
    "99000997": {
        "deprecated": false,
        "Dev_Desc": "증폭의 정수 : 천지 가르기 (각인)",
        "id": 99000997,
        "alias": "Contents.Item.Desc.9101140",
        "text": "Used to level up World Shaker.\nDecreases its Focus cost."
    },
    "99000998": {
        "deprecated": false,
        "Dev_Desc": "증폭의 정수 : 일섬 (각인)",
        "id": 99000998,
        "alias": "Contents.Item.Desc.9101141",
        "text": "Used to level up First Step.\nAdditionally inflicts Block Piercing."
    },
    "99000999": {
        "deprecated": false,
        "Dev_Desc": "극한의 정수 : 번개베기",
        "id": 99000999,
        "alias": "Contents.Item.Desc.9101142",
        "text": "Essence used for the evolution of Lightning Slash.\\nWhen evolving, the chance of being stunned by Sword Mark is increased."
    },
    "99001000": {
        "deprecated": false,
        "Dev_Desc": "돌파의 정수 : 번개베기",
        "id": 99001000,
        "alias": "Contents.Item.Desc.9101143",
        "text": "Essence used to evolve Lightning Slash.\\nInflicts additional attacks on enemies in stun state when evolving."
    },
    "99001001": {
        "deprecated": false,
        "Dev_Desc": "돌파의 정수 : 뛰어베기 (각인)",
        "id": 99001001,
        "alias": "Contents.Item.Desc.9101144",
        "text": "Used to level up Jumping Slash.\nIncreases the range."
    },
    "99001002": {
        "deprecated": false,
        "Dev_Desc": "돌파의 정수 : 올려베기 (각인)",
        "id": 99001002,
        "alias": "Contents.Item.Desc.9101145",
        "text": "Essence used for the evolution of slash.\\nWhen evolving, an additional finishing attack is applied after a chained attack."
    },
    "99001003": {
        "deprecated": false,
        "Dev_Desc": "극한의 정수 : 어검징표",
        "id": 99001003,
        "alias": "Contents.Item.Desc.9101146",
        "text": "Essence used for the evolution of the sword mark. \\nEvolution increases the range."
    },
    "99001004": {
        "deprecated": false,
        "Dev_Desc": "돌파의 정수 : 어검징표",
        "id": 99001004,
        "alias": "Contents.Item.Desc.9101147",
        "text": "Essence used for the evolution of the sword mark.\\nWhen evolving, the effect of stun is applied with a certain probability."
    },
    "99001005": {
        "deprecated": false,
        "Dev_Desc": "극한의 정수 : 구름베기",
        "id": 99001005,
        "alias": "Contents.Item.Desc.9101148",
        "text": "Essence used to evolve Cloud Slash. \\nEvolution reduces damage received by 60%."
    },
    "99001006": {
        "deprecated": false,
        "Dev_Desc": "돌파의 정수 : 구름베기",
        "id": 99001006,
        "alias": "Contents.Item.Desc.9101149",
        "text": "Essence used to evolve cloud slash.\\nWhen evolving, use continuous cloud slash on the target of Sword Sword Mark."
    },
    "99001007": {
        "deprecated": false,
        "Dev_Desc": "극한의 정수 : 천지가르기 (각인)",
        "id": 99001007,
        "alias": "Contents.Item.Desc.9101150",
        "text": "Used to level up World Shaker.\nIncreases Accuracy for enemy afflicted with Soul Stab."
    },
    "99001008": {
        "deprecated": false,
        "Dev_Desc": "극한의 정수 : 일섬 (각인)",
        "id": 99001008,
        "alias": "Contents.Item.Desc.9101151",
        "text": "Used to level up First Step.\nIncreases the range and damage for enemies afflicted with Soul Stab."
    },
    "99001009": {
        "deprecated": false,
        "Dev_Desc": "돌파의 정수 : 막기 (각인)",
        "id": 99001009,
        "alias": "Contents.Item.Desc.9101152",
        "text": "Used to level up Block.\nIncreases Parry chance."
    },
    "99001010": {
        "deprecated": false,
        "Dev_Desc": "증폭의 정수 : 어검징표 (각인)",
        "id": 99001010,
        "alias": "Contents.Item.Desc.9101153",
        "text": "Used to level up Soul Stab.\nAdditionally inflicts Stun."
    },
    "99001012": {
        "deprecated": false,
        "Dev_Desc": "증폭의 정수 : 구름베기 (각인)",
        "id": 99001012,
        "alias": "Contents.Item.Desc.9101155",
        "text": "Used to level up Cloud Slash.\nDecreases its cooldown."
    },
    "99001013": {
        "deprecated": false,
        "Dev_Desc": "증폭의 정수 : 번개베기 (각인)",
        "id": 99001013,
        "alias": "Contents.Item.Desc.9101156",
        "text": "Used to level up Lightning Slash.\nDeals an extra attack to the stunned enemy."
    },
    "99001018": {
        "deprecated": false,
        "Dev_Desc": "증폭의 정수 : 회천각 (각인)",
        "id": 99001018,
        "alias": "Contents.Item.Desc.9101210",
        "text": "Used to level up Cyclone Kick.\nDecreases its cooldown."
    },
    "99001019": {
        "deprecated": false,
        "Dev_Desc": "증폭의 정수 : 승룡각 (각인)",
        "id": 99001019,
        "alias": "Contents.Item.Desc.9101211",
        "text": "Used to level up Rising Dragon.\nHas a chance to stack Petrify on each strike."
    },
    "99001020": {
        "deprecated": false,
        "Dev_Desc": "증폭의 정수 : 횡이동 (각인)",
        "id": 99001020,
        "alias": "Contents.Item.Desc.9101212",
        "text": "Used to level up Traverse.\nDecreases its Vitality cost."
    },
    "99001028": {
        "deprecated": false,
        "Dev_Desc": "극한의 정수 : 회천각 (각인)",
        "id": 99001028,
        "alias": "Contents.Item.Desc.9101220",
        "text": "Used to level up Cyclone Kick.\nDecreases its Focus cost."
    },
    "99001029": {
        "deprecated": false,
        "Dev_Desc": "극한의 정수 : 승룡각 (각인)",
        "id": 99001029,
        "alias": "Contents.Item.Desc.9101221",
        "text": "Used to level up Rising Dragon.\nDecreases its cooldown."
    },
    "99001030": {
        "deprecated": false,
        "Dev_Desc": "극한의 정수 : 횡이동 (각인)",
        "id": 99001030,
        "alias": "Contents.Item.Desc.9101222",
        "text": "Used to level up Traverse.\nIncreases its range."
    },
    "99001031": {
        "deprecated": false,
        "Dev_Desc": "증폭의 정수 : 비염각 (각인)",
        "id": 99001031,
        "alias": "Contents.Item.Desc.9101223",
        "text": "Used to level up Tiger's Pounce.\nIncreases its charging distance."
    },
    "99001038": {
        "deprecated": false,
        "Dev_Desc": "돌파의 정수 : 회천각 (각인)",
        "id": 99001038,
        "alias": "Contents.Item.Desc.9101230",
        "text": "Used to level up Cyclone Kick.\nDeals damage increased relative to the Normal Attack Speed."
    },
    "99001039": {
        "deprecated": false,
        "Dev_Desc": "돌파의 정수 : 승룡각 (각인)",
        "id": 99001039,
        "alias": "Contents.Item.Desc.9101231",
        "text": "Used to level up Rising Dragon.\nHas a chance to additionally inflict Stun on the last hit."
    },
    "99001040": {
        "deprecated": false,
        "Dev_Desc": "증폭의 정수 : 절명각 (각인)",
        "id": 99001040,
        "alias": "Contents.Item.Desc.9101232",
        "text": "Used to level up Cutting Kick.\nDeals extra damage when attacking an enemy from behind."
    },
    "99001041": {
        "deprecated": false,
        "Dev_Desc": "극한의 정수 : 비염각 (각인)",
        "id": 99001041,
        "alias": "Contents.Item.Desc.9101233",
        "text": "Used to level up Tiger's Pounce.\nIncreases its damage."
    },
    "99001042": {
        "deprecated": false,
        "Dev_Desc": "증폭의 정수 : 맹호격 (각인)",
        "id": 99001042,
        "alias": "Contents.Item.Desc.9101234",
        "text": "Essence used to evolve the Fury. \\nEvolution increases the damage of the Fury."
    },
    "99001043": {
        "deprecated": false,
        "Dev_Desc": "극한의 정수 : 맹호격 (각인)",
        "id": 99001043,
        "alias": "Contents.Item.Desc.9101235",
        "text": "Essence used to evolve Furious Strike. \\nEvolution increases the chance of Stun."
    },
    "99001044": {
        "deprecated": false,
        "Dev_Desc": "돌파의 정수 : 다리걸기 (각인)",
        "id": 99001044,
        "alias": "Contents.Item.Desc.9101236",
        "text": "Essence used for the evolution of Legging.\\nWhen evolving, after using Legging, use it in conjunction with an enemy who is stunned."
    },
    "99001045": {
        "deprecated": false,
        "Dev_Desc": "돌파의 정수 : 맹호격 (각인)",
        "id": 99001045,
        "alias": "Contents.Item.Desc.9101237",
        "text": "Essence used for the evolution of the fierce attack.\\nWhen evolving, the stun effect is changed to the air effect.\\n\\n[Prerequisite]\\nLevel 9 or higher to enhance attack power"
    },
    "99001048": {
        "deprecated": false,
        "Dev_Desc": "증폭의 정수 : 다리걸기 (각인)",
        "id": 99001048,
        "alias": "Contents.Item.Desc.9101240",
        "text": "Used to level up Leg Sweep.\nReduces its cooldown."
    },
    "99001049": {
        "deprecated": false,
        "Dev_Desc": "증폭의 정수 : 승천권 (각인)",
        "id": 99001049,
        "alias": "Contents.Item.Desc.9101241",
        "text": "Used to level up Rising Fist.\nDeals damage increased relative to the Normal Attack Speed."
    },
    "99001050": {
        "deprecated": false,
        "Dev_Desc": "돌파의 정수 : 횡이동 (각인)",
        "id": 99001050,
        "alias": "Contents.Item.Desc.9101242",
        "text": "Used to level up Traverse.\nIncreases Evasion while casting Traverse."
    },
    "99001051": {
        "deprecated": false,
        "Dev_Desc": "돌파의 정수 : 비염각 (각인)",
        "id": 99001051,
        "alias": "Contents.Item.Desc.9101243",
        "text": "Used to level up Tiger's Pounce.\nDecreases its cooldown."
    },
    "99001052": {
        "deprecated": false,
        "Dev_Desc": "극한의 정수 : 절명각 (각인)",
        "id": 99001052,
        "alias": "Contents.Item.Desc.9101244",
        "text": "Used to level up Cutting Kick.\nGreatly decreases its Focus cost."
    },
    "99001053": {
        "deprecated": false,
        "Dev_Desc": "극한의 정수 : 붕권 (각인)",
        "id": 99001053,
        "alias": "Contents.Item.Desc.9101245",
        "text": "Essence used to evolve Bungwon.\\nWhen evolving, block penetration is increased by 7 while using Bungwon."
    },
    "99001054": {
        "deprecated": false,
        "Dev_Desc": "돌파의 정수 : 붕권 (각인)",
        "id": 99001054,
        "alias": "Contents.Item.Desc.9101246",
        "text": "Essence used to evolve Bungwon.\\nWhen evolving, it will hit up to 3 people within range."
    },
    "99001055": {
        "deprecated": false,
        "Dev_Desc": "돌파의 정수 : 승천권 (각인)",
        "id": 99001055,
        "alias": "Contents.Item.Desc.9101247",
        "text": "Essence used to evolve the Ascension Sphere. \\n When evolving, use the Ascension Sphere and link the Kakhwagak to an enemy in air state."
    },
    "99001056": {
        "deprecated": false,
        "Dev_Desc": "증폭의 정수: 개혈",
        "id": 99001056,
        "alias": "Contents.Item.Desc.9101248",
        "text": "\"개혈\"의 진화에 사용되는 정수입니다.\n진화 시 \"개혈\"의 지속시간이 2초 증가합니다."
    },
    "99001057": {
        "deprecated": false,
        "Dev_Desc": "극한의 정수: 개혈",
        "id": 99001057,
        "alias": "Contents.Item.Desc.9101249",
        "text": "\"개혈\"의 진화에 사용되는 정수입니다.\n진화 시 2초간 모든 이동 속도 감소 효과를 해제하고 면역 상태가 됩니다."
    },
    "99001058": {
        "deprecated": false,
        "Dev_Desc": "극한의 정수 : 다리걸기 (각인)",
        "id": 99001058,
        "alias": "Contents.Item.Desc.9101250",
        "text": "Used to level up Leg Sweep.\nIron Shoulder is used in combination."
    },
    "99001059": {
        "deprecated": false,
        "Dev_Desc": "극한의 정수 : 승천권 (각인)",
        "id": 99001059,
        "alias": "Contents.Item.Desc.9101251",
        "text": "Used to level up Rising Fist.\nCasts Iron Butterfly in combo."
    },
    "99001060": {
        "deprecated": false,
        "Dev_Desc": "돌파의 정수 : 절명각 (각인)",
        "id": 99001060,
        "alias": "Contents.Item.Desc.9101252",
        "text": "Used to level up Cutting Kick.\nDeals damage increased relative to the Normal Attack Speed."
    },
    "99001061": {
        "deprecated": false,
        "Dev_Desc": "증폭의 정수 : 붕권 (각인)",
        "id": 99001061,
        "alias": "Contents.Item.Desc.9101253",
        "text": "Used to level up Comet Strike.\nAttacks 3 enemies within its range."
    },
    "99001062": {
        "deprecated": false,
        "Dev_Desc": "돌파의 정수: 개혈",
        "id": 99001062,
        "alias": "Contents.Item.Desc.9101254",
        "text": "\"개혈\"의 진화에 사용되는 정수입니다.\n진화 시 8초간 모든 이동 속도 감소 효과를 해제하고 면역 상태가 되며, 통제 저항률이 15% 증가합니다.\n\n[선행 조건]\n무공 강화 단계 +9 이상"
    },
    "99001069": {
        "deprecated": false,
        "Dev_Desc": "일반 / 철벽 / 특화 / 각인",
        "id": 99001069,
        "alias": "Contents.Item.Desc.9100310",
        "text": "Defends against attacks coming from ahead.\nNormal Attack is switched while Fortification is effective.\nPress once more to disable Fortification."
    },
    "99001070": {
        "deprecated": false,
        "Dev_Desc": "일반 / 천벌 / 액티브 / 각인",
        "id": 99001070,
        "alias": "Contents.Item.Desc.9100311",
        "text": "Smashes with an axe to deal damage."
    },
    "99001071": {
        "deprecated": false,
        "Dev_Desc": "일반 / 붕괴 / 액티브 / 각인",
        "id": 99001071,
        "alias": "Contents.Item.Desc.9100312",
        "text": "Strikes upward with full force, then smashes down to deal damage."
    },
    "99001072": {
        "deprecated": false,
        "Dev_Desc": "일반 / 단련 / 패시브 / 각인",
        "id": 99001072,
        "alias": "Contents.Item.Desc.9100313",
        "text": "Consistently performs high-intensity training.\nIncreases HP."
    },
    "99001073": {
        "deprecated": false,
        "Dev_Desc": "충격 / 일반 도끼 무공서 (각인)",
        "id": 99001073,
        "alias": "Contents.Item.Desc.9100314",
        "text": "Disarms the iron wall and slams down the ax to generate a shockwave at the target's location to attack. \\nSoul Parrying can be used successfully."
    },
    "99001079": {
        "deprecated": false,
        "Dev_Desc": "상급 / 광풍 / 액티브 / 각인",
        "id": 99001079,
        "alias": "Contents.Item.Desc.9100320",
        "text": "Spins to attack nearby enemies.\nCan move while casting Hurricane.\nDecreases incoming damage while casting Hurricane."
    },
    "99001080": {
        "deprecated": false,
        "Dev_Desc": "상급 / 격돌 / 액티브 / 각인",
        "id": 99001080,
        "alias": "Contents.Item.Desc.9100321",
        "text": "Dashes forward and deals damage.\nHas a chance to inflict Petrify."
    },
    "99001081": {
        "deprecated": false,
        "Dev_Desc": "상급 / 기합 / 패시브 / 각인",
        "id": 99001081,
        "alias": "Contents.Item.Desc.9100322",
        "text": "Strongly stimulates every muscle in the body.\nIncreases STR."
    },
    "99001082": {
        "deprecated": false,
        "Dev_Desc": "상급 / 활력 / 패시브 / 각인",
        "id": 99001082,
        "alias": "Contents.Item.Desc.9100323",
        "text": "Performs active physical exercises.\nIncreases CON."
    },
    "99001083": {
        "deprecated": false,
        "Dev_Desc": "진노 / 상급 도끼 무공서 (각인)",
        "id": 99001083,
        "alias": "Contents.Item.Desc.9100324",
        "text": "Crossed and swung axes to make a series of quick attacks. \\nUsed on targets that are stunned or air."
    },
    "99001089": {
        "deprecated": false,
        "Dev_Desc": "희귀 / 불사 / 액티브 / 각인",
        "id": 99001089,
        "alias": "Contents.Item.Desc.9100330",
        "text": "Activates innate body ability.\nHeals relative to CON over time.\nHas a chance to be activated when hit."
    },
    "99001090": {
        "deprecated": false,
        "Dev_Desc": "희귀 / 처단 / 액티브 / 각인",
        "id": 99001090,
        "alias": "Contents.Item.Desc.9100331",
        "text": "Smashes enemy with all might.\nDeals damage and has a chance to inflict Stun.\nCan be used on a provoked and stunned enemy.\nCan be used in combo with Roar and Cyclone."
    },
    "99001091": {
        "deprecated": false,
        "Dev_Desc": "희귀 / 체질 / 패시브 / 각인",
        "id": 99001091,
        "alias": "Contents.Item.Desc.9100332",
        "text": "Enhances Heal ability.\nIncreases HP Tonic efficiency."
    },
    "99001092": {
        "deprecated": false,
        "Dev_Desc": "희귀 / 강철 / 패시브 / 각인",
        "id": 99001092,
        "alias": "Contents.Item.Desc.9100333",
        "text": "Strengthens the body as hard as iron.\nIncreases All Defense."
    },
    "99001099": {
        "deprecated": false,
        "Dev_Desc": "영웅 / 포효 / 액티브 / 각인",
        "id": 99001099,
        "alias": "Contents.Item.Desc.9100340",
        "text": "Roars ahead to provoke an enemy.\nIncreases the chance to activate Invincible for a certain period of time."
    },
    "99001100": {
        "deprecated": false,
        "Dev_Desc": "영웅 / 분노 / 액티브 / 각인",
        "id": 99001100,
        "alias": "Contents.Item.Desc.9100341",
        "text": "Deals powerful damage with blasting energy.\nBecomes enraged for a short while.\nNormal attack deals more damage while enraged.\nHas a chance to be activated when dealing attacks."
    },
    "99001101": {
        "deprecated": false,
        "Dev_Desc": "영웅 / 금강 / 패시브 / 각인",
        "id": 99001101,
        "alias": "Contents.Item.Desc.9100342",
        "text": "Trains for enduring attacks while in defense.\nIncreases Block."
    },
    "99001102": {
        "deprecated": false,
        "Dev_Desc": "영웅 / 정의 / 패시브",
        "id": 99001102,
        "alias": "Contents.Item.Desc.9100343",
        "text": "Strengthens basic attacks against enemies with status ailments. All basic attacks deal additional damage to targets with Stun and Air status."
    },
    "99001103": {
        "deprecated": false,
        "Dev_Desc": "부술연계Ⅰ",
        "id": 99001103,
        "alias": "Contents.Item.Desc.9100344",
        "text": "보스 몬스터 공격 시 일정 확률로 \"처단\"이 활성화됩니다.\n(사용 무공 활성화 대기시간 15초)"
    },
    "99001109": {
        "deprecated": false,
        "Dev_Desc": "전설 / 불굴 / 패시브 / 각인",
        "id": 99001109,
        "alias": "Contents.Item.Desc.9100350",
        "text": "Bears the enemy's attack with undying determination.\nIncreases Incoming Damage."
    },
    "99001110": {
        "deprecated": false,
        "Dev_Desc": "영웅 / 선풍 / 무기스킬 / 각인",
        "id": 99001110,
        "alias": "Contents.Item.Desc.9100351",
        "text": "Throws the axe to attack.\nHas a chance to pull the enemy and inflicts Stun."
    },
    "99001111": {
        "deprecated": false,
        "Dev_Desc": "전설 / 장벽 / 액티브 / 각인",
        "id": 99001111,
        "alias": "Contents.Item.Desc.9100352",
        "text": "Creates a barrier.\nDisables movement and defends the enemy's attack."
    },
    "99001120": {
        "deprecated": false,
        "Dev_Desc": "일반 / 결빙공 / 특화 / 각인",
        "id": 99001120,
        "alias": "Contents.Item.Desc.9100410",
        "text": "Protect yourself by enveloping yourself in ice.\\nProtects you from attacks from all directions for 4 seconds."
    },
    "99001121": {
        "deprecated": false,
        "Dev_Desc": "일반 / 연화 / 액티브 / 각인",
        "id": 99001121,
        "alias": "Contents.Item.Desc.9100411",
        "text": "Immediately infuses the target with fire, dealing damage.\\nOn a hit, you gain a Fire effect for 5.8 seconds that enables the use of a specific weapon."
    },
    "99001122": {
        "deprecated": false,
        "Dev_Desc": "일반 / 화련장 / 액티브 / 각인",
        "id": 99001122,
        "alias": "Contents.Item.Desc.9100412",
        "text": "Shoots fireballs to deal damage to enemy."
    },
    "99001123": {
        "deprecated": false,
        "Dev_Desc": "일반 / 순환 / 패시브 / 각인",
        "id": 99001123,
        "alias": "Contents.Item.Desc.9100413",
        "text": "Realizes the circulation of heat and cold.\nIncreases INT."
    },
    "99001124": {
        "deprecated": false,
        "Dev_Desc": "일반 / 빙륜참 / 액션 (각인)",
        "id": 99001124,
        "alias": "Contents.Item.Desc.9100414",
        "text": "Disarms the Ice Ball and fires a spinning ice blade. \\nCan be used by manually pressing the Attack button."
    },
    "99001130": {
        "deprecated": false,
        "Dev_Desc": "상급 / 얼음창 / 액티브 / 각인",
        "id": 99001130,
        "alias": "Contents.Item.Desc.9100420",
        "text": "Summons multiple ice spears and fires them at the enemy.\\nApplies a slow effect that reduces movement speed with a chance.\\n\\n[Effect]\\nMovement speed reduction rate 60%"
    },
    "99001131": {
        "deprecated": false,
        "Dev_Desc": "상급 / 유성 / 액티브 / 각인",
        "id": 99001131,
        "alias": "Contents.Item.Desc.9100421",
        "text": "Rains down meteors to deal damage and has a chance to inflict Burn.\nAffects up to 3 enemies within range."
    },
    "99001132": {
        "deprecated": false,
        "Dev_Desc": "상급 / 냉정 / 패시브 / 각인",
        "id": 99001132,
        "alias": "Contents.Item.Desc.9100422",
        "text": "Calms the mind to maintain a cold heart.\nIncreases Bangle Attack."
    },
    "99001133": {
        "deprecated": false,
        "Dev_Desc": "상급 / 열정 / 패시브 / 각인",
        "id": 99001133,
        "alias": "Contents.Item.Desc.9100423",
        "text": "Trains with a great passion for martial arts.\nIncreases Force Attack."
    },
    "99001134": {
        "deprecated": false,
        "Dev_Desc": "상급 / 홍염 / 패시브 / 각인",
        "id": 99001134,
        "alias": "Contents.Item.Desc.9100424",
        "text": "Musters up a fiercer and more fiery flame.\nInflicts Flame Boost that decreases Force Defense when the enemy is inflicted by Burn."
    },
    "99001135": {
        "deprecated": false,
        "Dev_Desc": "희귀 / 화빙연포 / 액션 (각인)",
        "id": 99001135,
        "alias": "Contents.Item.Desc.9100425",
        "text": "Fire and ice bullets are fired in a burst. \\nCan be used by manually pressing the attack button."
    },
    "99001140": {
        "deprecated": false,
        "Dev_Desc": "희귀 / 회진보 / 액티브 / 각인",
        "id": 99001140,
        "alias": "Contents.Item.Desc.9100430",
        "text": "Transforms into fire and ashes, dispels the stun effect and evades backwards. When used, increases control resistance for 5 seconds.\\n\\n[effect]\\ncontrol resistance 8%"
    },
    "99001141": {
        "deprecated": false,
        "Dev_Desc": "희귀 / 비륜연휘 / 액티브 / 각인",
        "id": 99001141,
        "alias": "Contents.Item.Desc.9100431",
        "text": "Shoots a ball of superheated fire, dealing damage.\\nCan be used by consuming the Ignition effect."
    },
    "99001142": {
        "deprecated": false,
        "Dev_Desc": "희귀 / 빙백 / 패시브 / 각인",
        "id": 99001142,
        "alias": "Contents.Item.Desc.9100432",
        "text": "Increases WIS by understanding the nature of ice."
    },
    "99001143": {
        "deprecated": false,
        "Dev_Desc": "희귀 / 폭열 / 패시브 / 각인",
        "id": 99001143,
        "alias": "Contents.Item.Desc.9100433",
        "text": "Increases Force Piercing Damage by understanding the nature of fire."
    },
    "99001150": {
        "deprecated": false,
        "Dev_Desc": "영웅 / 봉황시 / 액티브 / 각인",
        "id": 99001150,
        "alias": "Contents.Item.Desc.9100440",
        "text": "Jumps up in the air and rapidly shoots blazing feathers.\nDeals damage which increases relative to WIS."
    },
    "99001151": {
        "deprecated": false,
        "Dev_Desc": "영웅 / 용렬빙하 / 액티브 / 각인",
        "id": 99001151,
        "alias": "Contents.Item.Desc.9100441",
        "text": "Creates a glacier that rises forward. Has a chance to inflict Freeze which hinders movement.\nAffects up to 3 enemies within range."
    },
    "99001152": {
        "deprecated": false,
        "Dev_Desc": "영웅 / 화륜 / 액티브 / 각인",
        "id": 99001152,
        "alias": "Contents.Item.Desc.9100442",
        "text": "Inflicts Heater, which increases the party members' Normal Attack Speed and Technique Attack Speed by discharging the inner flame."
    },
    "99001153": {
        "deprecated": false,
        "Dev_Desc": "영웅 / 천빙 / 패시브 / 각인",
        "id": 99001153,
        "alias": "Contents.Item.Desc.9100443",
        "text": "Attacks a target that is incapacitated by the chill even more mercilessly.\\nApplies additional damage when attacking a frozen target.\\nAdditional damage has a 3 second cooldown."
    },
    "99001154": {
        "deprecated": false,
        "Dev_Desc": "영웅 / 염제 / 패시브 / 각인",
        "id": 99001154,
        "alias": "Contents.Item.Desc.9100444",
        "text": "만물이 띠는 기운에 통달합니다.\n모든 속성 공격 증폭이 증가합니다.\n\n[효과]\n모든 속성 공격 증폭 +7%"
    },
    "99001161": {
        "deprecated": false,
        "Dev_Desc": "전설 / 화광소천 / 액티브 / 각인",
        "id": 99001161,
        "alias": "Contents.Item.Desc.9100451",
        "text": "Forms the ultimate firestorm, pulling it in with a chance, then exploding it and knocking it back. \\n Hits up to 5 people within range."
    },
    "99001162": {
        "deprecated": false,
        "Dev_Desc": "전설 / 빙정 / 패시브 / 각인",
        "id": 99001162,
        "alias": "Contents.Item.Desc.9100452",
        "text": "Masters an ice technique.\nIncreases the chance of Freeze\non the enemy afflicted with Slow."
    },
    "99001163": {
        "deprecated": false,
        "Dev_Desc": "전설 / 조화 / 패시브 / 각인",
        "id": 99001163,
        "alias": "Contents.Item.Desc.9100453",
        "text": "Accomplishes the synergy of ice and fire.\nIncreases Technique Attack Speed."
    },
    "99001171": {
        "deprecated": false,
        "Dev_Desc": "일반 / 추적화살 / 액티브 / 각인",
        "id": 99001171,
        "alias": "Contents.Item.Desc.9100510",
        "text": "Relentlessly tracks the enemy and deals damage."
    },
    "99001172": {
        "deprecated": false,
        "Dev_Desc": "일반 / 다발화살 / 액티브 / 각인",
        "id": 99001172,
        "alias": "Contents.Item.Desc.9100511",
        "text": "Shoots a bundle of arrows to deal damage."
    },
    "99001173": {
        "deprecated": false,
        "Dev_Desc": "일반 / 조준 / 패시브 / 각인",
        "id": 99001173,
        "alias": "Contents.Item.Desc.9100512",
        "text": "Calmly aims at the target for an accurate shot.\nIncreases Ranged Attack."
    },
    "99001174": {
        "deprecated": false,
        "Dev_Desc": "일반 / 화살비 / 특화 / 각인",
        "id": 99001174,
        "alias": "Contents.Item.Desc.9100513",
        "text": "Pours arrows over the enemy to deal damage."
    },
    "99001175": {
        "deprecated": false,
        "Dev_Desc": "전진사격 / EQ",
        "id": 99001175,
        "alias": "Contents.Item.Desc.9100514"
    },
    "99001181": {
        "deprecated": false,
        "Dev_Desc": "상급 / 다중사격 / 액티브 / 각인",
        "id": 99001181,
        "alias": "Contents.Item.Desc.9100520",
        "text": "Rapidly shoots multiple arrows to deal damage to an enemy."
    },
    "99001183": {
        "deprecated": false,
        "Dev_Desc": "상급 / 직감 / 패시브 / 각인",
        "id": 99001183,
        "alias": "Contents.Item.Desc.9100522",
        "text": "Concentrates all senses to enhance physical ability.\nIncreases AGI and DEX."
    },
    "99001184": {
        "deprecated": false,
        "Dev_Desc": "일반 / 출혈화살 / 패시브 / 각인",
        "id": 99001184,
        "alias": "Contents.Item.Desc.9100523",
        "text": "Shoots an arrow that has a chance to inflict Bleed on a target."
    },
    "99001185": {
        "deprecated": false,
        "Dev_Desc": "연사 / QQ",
        "id": 99001185,
        "alias": "Contents.Item.Desc.9100524",
        "text": "빠르게 시위를 당겨 대상에게 화살을 날립니다. 소울 패링 기절 대상에게 공격 버튼을 수동으로 눌러 사용 가능합니다."
    },
    "99001191": {
        "deprecated": false,
        "Dev_Desc": "희귀 / 살상명령 / 액티브 / 각인",
        "id": 99001191,
        "alias": "Contents.Item.Desc.9100530",
        "text": "Greatly increases Normal Attack Speed for a short while."
    },
    "99001192": {
        "deprecated": false,
        "Dev_Desc": "희귀 / 후퇴사격 / 액티브 / 각인",
        "id": 99001192,
        "alias": "Contents.Item.Desc.9100531",
        "text": "Quickly darts back and shoots an arrow at the enemy."
    },
    "99001193": {
        "deprecated": false,
        "Dev_Desc": "희귀 / 연마 / 패시브 / 각인",
        "id": 99001193,
        "alias": "Contents.Item.Desc.9100532",
        "text": "Pierces the target by tightly pulling back on the bow.\nIncreases Ranged Physical Piercing."
    },
    "99001194": {
        "deprecated": false,
        "Dev_Desc": "희귀 / 속사 / 패시브 / 각인",
        "id": 99001194,
        "alias": "Contents.Item.Desc.9100533",
        "text": "Plucks the bowstring faster.\nIncreases Normal Attack Speed."
    },
    "99001195": {
        "deprecated": false,
        "Dev_Desc": "희귀 / 깊은상처 / 패시브 / 각인",
        "id": 99001195,
        "alias": "Contents.Item.Desc.9100534",
        "text": "The sharp arrowhead causes a deep wound.\nIncreases the duration of Bleed."
    },
    "99001201": {
        "deprecated": false,
        "Dev_Desc": "영웅 / 반마화살 / 액티브 / 각인",
        "id": 99001201,
        "alias": "Contents.Item.Desc.9100540",
        "text": "The arrow removes all technique buffs on the target."
    },
    "99001202": {
        "deprecated": false,
        "Dev_Desc": "영웅 / 조준사격 / 액티브 / 각인",
        "id": 99001202,
        "alias": "Contents.Item.Desc.9100541",
        "text": "Draws the bow to shoot an arrow with power.\nGreatly increases Ranged Critical Rate and has a chance to inflict Stun."
    },
    "99001203": {
        "deprecated": false,
        "Dev_Desc": "영웅 / 몰입 / 패시브 / 각인",
        "id": 99001203,
        "alias": "Contents.Item.Desc.9100542",
        "text": "Puts all distracting thoughts behind to concentrate on the battle.\nIncreases Ranged Critical Rate and Critical Bonus."
    },
    "99001204": {
        "deprecated": false,
        "Dev_Desc": "영웅 / 백발백중 / 패시브 / 각인",
        "id": 99001204,
        "alias": "Contents.Item.Desc.9100543",
        "text": "Increases Ranged Accuracy with infallible bow skills."
    },
    "99001206": {
        "deprecated": false,
        "Dev_Desc": "영웅 / 강사 / 패시브 / 각인",
        "id": 99001206,
        "alias": "Contents.Item.Desc.9100545",
        "text": "Has a chance to inflict Bleed on normal critical hit."
    },
    "99001207": {
        "deprecated": false,
        "Dev_Desc": "신궁",
        "id": 99001207,
        "alias": "Contents.Item.Desc.9100546",
        "text": "귀신같은 실력으로 활을 자유자재로 다룹니다.\n\n[효과]\nPVP 공격력 +3\nPVP 관통력 +5"
    },
    "99001212": {
        "deprecated": false,
        "Dev_Desc": "전설 / 혈상 / 패시브 / 각인",
        "id": 99001212,
        "alias": "Contents.Item.Desc.9100551",
        "text": "Inflicts Bleed and reduces Heal"
    },
    "99001213": {
        "deprecated": false,
        "Dev_Desc": "살우",
        "id": 99001213,
        "alias": "Contents.Item.Desc.9100552"
    },
    "99001222": {
        "deprecated": false,
        "Dev_Desc": "상급 / 생령치유 / 액티브 / 각인",
        "id": 99001222,
        "alias": "Contents.Item.Desc.9100610",
        "text": "Heals up to 2 nearby party members with divine energy in a row."
    },
    "99001223": {
        "deprecated": false,
        "Dev_Desc": "일반 / 연섬뢰 / 액티브 / 각인",
        "id": 99001223,
        "alias": "Contents.Item.Desc.9100611",
        "text": "Deals multiple damage to the target instantly."
    },
    "99001224": {
        "deprecated": false,
        "Dev_Desc": "일반 / 강섬뢰 / 액티브 / 각인",
        "id": 99001224,
        "alias": "Contents.Item.Desc.9100612",
        "text": "Deals a strong attack to the target."
    },
    "99001225": {
        "deprecated": false,
        "Dev_Desc": "일반 / 가호 / 패시브 / 각인",
        "id": 99001225,
        "alias": "Contents.Item.Desc.9100613",
        "text": "Increases Focus Regen thanks to blessings from the heavens."
    },
    "99001226": {
        "deprecated": false,
        "Dev_Desc": "생령폭격 / EQ",
        "id": 99001226,
        "alias": "Contents.Item.Desc.9100614",
        "text": "소울 패링 성공 시 강력한 공격으로 반격합니다."
    },
    "99001232": {
        "deprecated": false,
        "Dev_Desc": "일반 / 생령합일 / 특화 / 각인",
        "id": 99001232,
        "alias": "Contents.Item.Desc.9100620",
        "text": "United with the Spirit for a period of time to avoid most attacks. Attack and Roll cannot be used while united, and movement speed decreases."
    },
    "99001233": {
        "deprecated": false,
        "Dev_Desc": "상급 / 심기일전 / 액티브 / 각인",
        "id": 99001233,
        "alias": "Contents.Item.Desc.9100621",
        "text": "Increases Attack for the whole party for a certain time period."
    },
    "99001234": {
        "deprecated": false,
        "Dev_Desc": "영웅 / 현기 / 패시브 / 각인",
        "id": 99001234,
        "alias": "Contents.Item.Desc.9100622",
        "text": "Heal is increased through a deeper understanding of healing."
    },
    "99001235": {
        "deprecated": false,
        "Dev_Desc": "상급 / 현자 / 패시브 / 각인",
        "id": 99001235,
        "alias": "Contents.Item.Desc.9100623",
        "text": "Increases WIS and INT through deep concentration."
    },
    "99001236": {
        "deprecated": false,
        "Dev_Desc": "굉섬뢰 / Q",
        "id": 99001236,
        "alias": "Contents.Item.Desc.9100624",
        "text": "소울 패링 기절 상태의 대상에게 강력한 공격을 가합니다."
    },
    "99001242": {
        "deprecated": false,
        "Dev_Desc": "희귀 / 치유지대 / 액티브 / 각인",
        "id": 99001242,
        "alias": "Contents.Item.Desc.9100630",
        "text": "Install a totem to heal nearby party members over time."
    },
    "99001243": {
        "deprecated": false,
        "Dev_Desc": "희귀 / 청화 / 액티브 / 각인",
        "id": 99001243,
        "alias": "Contents.Item.Desc.9100631",
        "text": "Has a chance to burn a part of the target's Focus by attacking them with the power of auspicious blue flame."
    },
    "99001244": {
        "deprecated": false,
        "Dev_Desc": "희귀 / 득음 / 패시브 / 각인",
        "id": 99001244,
        "alias": "Contents.Item.Desc.9100632",
        "text": "Deals greater damage with a Bell by realizing the power of pitch."
    },
    "99001252": {
        "deprecated": false,
        "Dev_Desc": "영웅 / 심판 / 액티브 / 각인",
        "id": 99001252,
        "alias": "Contents.Item.Desc.9100640",
        "text": "Deals a powerful strike, smashing down from above."
    },
    "99001253": {
        "deprecated": false,
        "Dev_Desc": "영웅 / 수호 / 액티브 / 각인",
        "id": 99001253,
        "alias": "Contents.Item.Desc.9100641",
        "text": "Protects the target with divine energy to reduce damage taken for 25 seconds.\\n\\n[Effect]\\nReduce damage taken by 20%"
    },
    "99001254": {
        "deprecated": false,
        "Dev_Desc": "영웅 / 구원 / 액티브 / 각인",
        "id": 99001254,
        "alias": "Contents.Item.Desc.9100642",
        "text": "Removes Stun, Freeze, and Slow effects from the party and increases CC Resist for a certain period of time."
    },
    "99001255": {
        "deprecated": false,
        "Dev_Desc": "영웅 / 체화 / 패시브 / 각인",
        "id": 99001255,
        "alias": "Contents.Item.Desc.9100643",
        "text": "Increases weapon attack power by embodied divine energy into the body.\\n\\n[effect]\\nweapon attack 2"
    },
    "99001256": {
        "deprecated": false,
        "Dev_Desc": "영웅 / 은총 / 패시브 / 각인",
        "id": 99001256,
        "alias": "Contents.Item.Desc.9100644",
        "text": "Healing from Heaven's Grace is increased.\\n\\n[Effect]\\nhealing done by 3.0%"
    },
    "99001257": {
        "deprecated": false,
        "Dev_Desc": "영웅 / 치환 / 패시브",
        "id": 99001257,
        "alias": "Contents.Item.Desc.9100645",
        "text": "Basic attacks have a chance to deal additional damage proportional to healing power."
    },
    "99001258": {
        "deprecated": false,
        "Dev_Desc": "항음",
        "id": 99001258,
        "alias": "Contents.Item.Desc.9100646",
        "text": "항마의 기운을 음에 담아냅니다.\n\n[효과]\nPVE 공격력 +10, 보스 공격력 +5"
    },
    "99001262": {
        "deprecated": false,
        "Dev_Desc": "전설 / 광명청음 / 액티브 / 각인",
        "id": 99001262,
        "alias": "Contents.Item.Desc.9100650",
        "text": "Envelopes all party members with divine light and sound. Restores a large amount of HP and protects against damage for 5 seconds."
    },
    "99001263": {
        "deprecated": false,
        "Dev_Desc": "전설 / 통달 / 패시브 / 각인",
        "id": 99001263,
        "alias": "Contents.Item.Desc.9100651",
        "text": "More easily resist CC by honing your skill in all things."
    },
    "99001273": {
        "deprecated": false,
        "Dev_Desc": "증폭의 정수 : 천벌 (각인)",
        "id": 99001273,
        "alias": "Contents.Item.Desc.9101310",
        "text": "Used to level up Divine Wrath.\nIncreases its damage."
    },
    "99001274": {
        "deprecated": false,
        "Dev_Desc": "증폭의 정수 : 붕괴 (각인)",
        "id": 99001274,
        "alias": "Contents.Item.Desc.9101311",
        "text": "Used to level up Breakdown.\nDecreases its Focus cost."
    },
    "99001275": {
        "deprecated": false,
        "Dev_Desc": "증폭의 정수 : 철벽 (각인)",
        "id": 99001275,
        "alias": "Contents.Item.Desc.9101312",
        "text": "Used to level up Fortification.\nIncreases its Parry Chance."
    },
    "99001283": {
        "deprecated": false,
        "Dev_Desc": "극한의 정수 : 천벌 (각인)",
        "id": 99001283,
        "alias": "Contents.Item.Desc.9101320",
        "text": "Used to level up Divine Wrath.\nIncreases its cooldown."
    },
    "99001284": {
        "deprecated": false,
        "Dev_Desc": "극한의 정수 : 붕괴 (각인)",
        "id": 99001284,
        "alias": "Contents.Item.Desc.9101321",
        "text": "Used to level up Breakdown.\nIncreases its cooldown."
    },
    "99001285": {
        "deprecated": false,
        "Dev_Desc": "증폭의 정수 : 격돌 (각인)",
        "id": 99001285,
        "alias": "Contents.Item.Desc.9101322",
        "text": "Used to level up Slam.\nDecreases its Focus cost."
    },
    "99001286": {
        "deprecated": false,
        "Dev_Desc": "증폭의 정수 : 광풍 (각인)",
        "id": 99001286,
        "alias": "Contents.Item.Desc.9101323",
        "text": "Used to level up Hurricane.\nIncreases Move Speed while casting Hurricane."
    },
    "99001287": {
        "deprecated": false,
        "Dev_Desc": "돌파의 정수 : 격돌",
        "id": 99001287,
        "alias": "Contents.Item.Desc.9101324",
        "text": "Essence used to evolve Clash.\\nWhen evolving, the range increases, and the stun effect is applied with a certain probability during an iron wall."
    },
    "99001293": {
        "deprecated": false,
        "Dev_Desc": "돌파의 정수 : 천벌 (각인)",
        "id": 99001293,
        "alias": "Contents.Item.Desc.9101330",
        "text": "Used to level up Divine Wrath.\nHas a chance to accelerate attacks up to 5 times."
    },
    "99001294": {
        "deprecated": false,
        "Dev_Desc": "돌파의 정수 : 붕괴 (각인)",
        "id": 99001294,
        "alias": "Contents.Item.Desc.9101331",
        "text": "Used to level up Breakdown.\nDeals extra damage relative to CON."
    },
    "99001295": {
        "deprecated": false,
        "Dev_Desc": "극한의 정수 : 격돌 (각인)",
        "id": 99001295,
        "alias": "Contents.Item.Desc.9101332",
        "text": "Used to level up Slam.\nHas a chance to activate Rage upon accurate hit."
    },
    "99001296": {
        "deprecated": false,
        "Dev_Desc": "극한의 정수 : 광풍 (각인)",
        "id": 99001296,
        "alias": "Contents.Item.Desc.9101333",
        "text": "Used to level up Hurricane.\nDefends incoming attacks and increases the chance to activate Invincible for a certain period of time."
    },
    "99001297": {
        "deprecated": false,
        "Dev_Desc": "증폭의 정수 : 처단 (각인)",
        "id": 99001297,
        "alias": "Contents.Item.Desc.9101334",
        "text": "Used to level up Eradicate.\nIncreases its cooldown."
    },
    "99001298": {
        "deprecated": false,
        "Dev_Desc": "돌파의 정수 : 분노",
        "id": 99001298,
        "alias": "Contents.Item.Desc.9101335",
        "text": "Essence used to evolve anger.\\nRage effect duration increases by 3 seconds.\\nThe activation chance increases when you hit a whirlwind or death penalty.\\n\\n[Prerequisite]\\nEnhancement Level 9 or higher"
    },
    "99001299": {
        "deprecated": false,
        "Dev_Desc": "극한의 정수 : 선풍",
        "id": 99001299,
        "alias": "Contents.Item.Desc.9101336",
        "text": "Essence used to evolve the whirlwind. \\nWhen evolving, there is a chance to apply the pull effect."
    },
    "99001300": {
        "deprecated": false,
        "Dev_Desc": "돌파의 정수 : 선풍",
        "id": 99001300,
        "alias": "Contents.Item.Desc.9101337",
        "text": "Essence used to evolve the whirlwind.\\nInflicts an additional attack on the drawn enemy when evolving.\\n\\n[Prerequisite]\\nEnhancement Level 9 or higher"
    },
    "99001303": {
        "deprecated": false,
        "Dev_Desc": "증폭의 정수 : 불사 (각인)",
        "id": 99001303,
        "alias": "Contents.Item.Desc.9101340",
        "text": "Used to level up Invincible.\nHas a higher chance to enable when HP drops to a certain level.\nA successful defense increases the chance of activation."
    },
    "99001304": {
        "deprecated": false,
        "Dev_Desc": "증폭의 정수 : 분노 (각인)",
        "id": 99001304,
        "alias": "Contents.Item.Desc.9101341",
        "text": "Used to level up Rage.\nIncreases STR when dealing attack."
    },
    "99001305": {
        "deprecated": false,
        "Dev_Desc": "극한의 정수 : 철벽 (각인)",
        "id": 99001305,
        "alias": "Contents.Item.Desc.9101342",
        "text": "Used to level up Fortification.\nCan use Slam, Roar, and Invincible while casting Fortification."
    },
    "99001306": {
        "deprecated": false,
        "Dev_Desc": "돌파의 정수 : 광풍 (각인)",
        "id": 99001306,
        "alias": "Contents.Item.Desc.9101343",
        "text": "Used to level up Hurricane.\nAdditionally inflicts Petrify."
    },
    "99001307": {
        "deprecated": false,
        "Dev_Desc": "돌파의 정수 : 불사",
        "id": 99001307,
        "alias": "Contents.Item.Desc.9101344",
        "text": "Used to level up Eradicate.\nAttacks up to 3 enemies within range."
    },
    "99001308": {
        "deprecated": false,
        "Dev_Desc": "극한의 정수 : 처단 ",
        "id": 99001308,
        "alias": "Contents.Item.Desc.9101345",
        "text": "Essence used for the evolution of punishment. \\n When evolving, damage increases in proportion to health."
    },
    "99001309": {
        "deprecated": false,
        "Dev_Desc": "돌파의 정수 : 처단",
        "id": 99001309,
        "alias": "Contents.Item.Desc.9101346",
        "text": "Essence used for the evolution of Punishment.\\nWhen evolving, it converts to wide-area damage, and hits up to 3 people within range.\\n\\n[Prerequisite]\\nEnhancement Level 9 or higher"
    },
    "99001310": {
        "deprecated": false,
        "Dev_Desc": "극한의 정수 : 포효",
        "id": 99001310,
        "alias": "Contents.Item.Desc.9101347",
        "text": "Essence used to evolve Roar.\\nWhen evolving, damage taken during Roar is reduced by 8%."
    },
    "99001311": {
        "deprecated": false,
        "Dev_Desc": "돌파의 정수 : 포효",
        "id": 99001311,
        "alias": "Contents.Item.Desc.9101348",
        "text": "Essence used to evolve Roar.\\nConverts to wide-area damage when evolving. Hits up to 3 people within range.\\n\\n[Prerequisite]\\nEnhancement Level 9 or higher"
    },
    "99001313": {
        "deprecated": false,
        "Dev_Desc": "극한의 정수 : 불사 (각인)",
        "id": 99001313,
        "alias": "Contents.Item.Desc.9101350",
        "text": "Used to level up Invincible.\nIncreases CC Resist while casting Invincible."
    },
    "99001314": {
        "deprecated": false,
        "Dev_Desc": "극한의 정수 : 분노 (각인)",
        "id": 99001314,
        "alias": "Contents.Item.Desc.9101351",
        "text": "Used to level up Rage.\nHas a chance to be activated upon accurate hit of Cyclone and Eradicate."
    },
    "99001315": {
        "deprecated": false,
        "Dev_Desc": "돌파의 정수 : 철벽 (각인)",
        "id": 99001315,
        "alias": "Contents.Item.Desc.9101352",
        "text": "Used to level up Fortification.\nIncreases Blocked Damage Down while casting Fortification."
    },
    "99001316": {
        "deprecated": false,
        "Dev_Desc": "증폭의 정수 : 포효 (각인)",
        "id": 99001316,
        "alias": "Contents.Item.Desc.9101353",
        "text": "Used to level up Roar.\nProvokes up to 3 enemies within range."
    },
    "99001317": {
        "deprecated": false,
        "Dev_Desc": "증폭의 정수 : 선풍 (각인)",
        "id": 99001317,
        "alias": "Contents.Item.Desc.9101354",
        "text": "Used to level up Cyclone.\nDeals an extra attack to the pulled enemy."
    },
    "99001324": {
        "deprecated": false,
        "Dev_Desc": "증폭의 정수 : 결빙공 (각인)",
        "id": 99001324,
        "alias": "Contents.Item.Desc.9101410",
        "text": "Essence used to evolve the Iceball. \\nEvolution reduces the Iceball's energy consumption by 100."
    },
    "99001325": {
        "deprecated": false,
        "Dev_Desc": "증폭의 정수 : 연화 (각인)",
        "id": 99001325,
        "alias": "Contents.Item.Desc.9101411",
        "text": "Essence used for the evolution of softening.\\nEvolves with a chance to inflict Burn effect."
    },
    "99001326": {
        "deprecated": false,
        "Dev_Desc": "증폭의 정수 : 화련장 (각인)",
        "id": 99001326,
        "alias": "Contents.Item.Desc.9101412",
        "text": "Essence used for the evolution of the Hwa Ryeonjang. \\n When evolving, damage increases in proportion to intelligence."
    },
    "99001334": {
        "deprecated": false,
        "Dev_Desc": "극한의 정수 : 결빙공 (각인)",
        "id": 99001334,
        "alias": "Contents.Item.Desc.9101420",
        "text": "Essence used to evolve the Freezer.\\nIf the defense succeeds during evolution, damage is applied to the attacked target."
    },
    "99001335": {
        "deprecated": false,
        "Dev_Desc": "극한의 정수 : 연화 (각인)",
        "id": 99001335,
        "alias": "Contents.Item.Desc.9101421",
        "text": "Essence used to evolve softening. \\nEvolving reduces the cooldown of softening by 2 seconds."
    },
    "99001336": {
        "deprecated": false,
        "Dev_Desc": "증폭의 정수 : 얼음창 (각인)",
        "id": 99001336,
        "alias": "Contents.Item.Desc.9101422",
        "text": "Essence used to evolve Ice Lance. \\n Evolution reduces the strength consumption of Ice Lance by 2."
    },
    "99001344": {
        "deprecated": false,
        "Dev_Desc": "돌파의 정수 : 결빙공 (각인)",
        "id": 99001344,
        "alias": "Contents.Item.Desc.9101430",
        "text": "Essence used for the evolution of the Ice Ball.\\nIf you succeed in defending during evolution, there is a chance to apply the Slow effect."
    },
    "99001345": {
        "deprecated": false,
        "Dev_Desc": "극한의 정수 : 화련장 (각인)",
        "id": 99001345,
        "alias": "Contents.Item.Desc.9101431",
        "text": "Essence used for the evolution of the Hwa Ryeonjang. \\n When evolving, it will be converted into wide-area damage, and it will hit up to 3 people within range."
    },
    "99001346": {
        "deprecated": false,
        "Dev_Desc": "극한의 정수 : 얼음창 (각인)",
        "id": 99001346,
        "alias": "Contents.Item.Desc.9101432",
        "text": "Essence used to evolve Ice Lance. \\n Evolving reduces the cooldown of Ice Lance by 2 seconds."
    },
    "99001347": {
        "deprecated": false,
        "Dev_Desc": "증폭의 정수 : 유성 (각인)",
        "id": 99001347,
        "alias": "Contents.Item.Desc.9101433",
        "text": "Essence used to evolve meteors.\\nWhen evolving, there is a chance to inflict Fire effect on yourself for 5.8 seconds."
    },
    "99001348": {
        "deprecated": false,
        "Dev_Desc": "증폭의 정수 : 회진보 (각인)",
        "id": 99001348,
        "alias": "Contents.Item.Desc.9101434",
        "text": "Essence used to evolve Hoejinbo. \\n When evolving, the power consumption of Hoejinbo is reduced by 4."
    },
    "99001349": {
        "deprecated": false,
        "Dev_Desc": "극한의 정수 : 회진보 (각인)",
        "id": 99001349,
        "alias": "Contents.Item.Desc.9101435",
        "text": "Essence used to evolve the roundabout. \\nEvolution reduces the cooldown of the roundabout by 5 seconds."
    },
    "99001350": {
        "deprecated": false,
        "Dev_Desc": "돌파의 정수 : 회진보 (각인)",
        "id": 99001350,
        "alias": "Contents.Item.Desc.9101436",
        "text": "Essence used to evolve Hoejinbo.\\nWhen evolving, after using Hoejinbo, HP is restored in proportion to intelligence."
    },
    "99001351": {
        "deprecated": false,
        "Dev_Desc": "돌파의 정수 : 비륜연휘 (각인)",
        "id": 99001351,
        "alias": "Contents.Item.Desc.9101437",
        "text": "Essence used for the evolution of Flying Rifle.\\nWhen evolving, the casting time of Flying Rhythm is reduced.\\n\\n[Prerequisite]\\nEnhancement Level 9 or higher"
    },
    "99001354": {
        "deprecated": false,
        "Dev_Desc": "돌파의 정수 : 연화 (각인)",
        "id": 99001354,
        "alias": "Contents.Item.Desc.9101440",
        "text": "Essence used to evolve softening.\\nWhen evolving, softening accuracy is increased by 25%.\\n\\n[Prerequisite]\\nLevel 9 or higher of non-gong enhancement"
    },
    "99001355": {
        "deprecated": false,
        "Dev_Desc": "돌파의 정수 : 화련장 (각인)",
        "id": 99001355,
        "alias": "Contents.Item.Desc.9101441",
        "text": "Essence used for the evolution of the HwaRyeonjang.\\nWhen evolving, there is a chance to give yourself the Ignition effect for 5.8 seconds."
    },
    "99001356": {
        "deprecated": false,
        "Dev_Desc": "돌파의 정수 : 얼음창 (각인)",
        "id": 99001356,
        "alias": "Contents.Item.Desc.9101442",
        "text": "Essence used to evolve Ice Spear.\\nWhen evolving, additionally applies the Freeze effect with a certain probability."
    },
    "99001357": {
        "deprecated": false,
        "Dev_Desc": "극한의 정수 : 유성 (각인)",
        "id": 99001357,
        "alias": "Contents.Item.Desc.9101443",
        "text": "Essence used to evolve meteors.\\nWhen evolving, fire an additional icy meteor, with a chance to apply a slow effect."
    },
    "99001358": {
        "deprecated": false,
        "Dev_Desc": "증폭의 정수 : 비륜연휘 (각인)",
        "id": 99001358,
        "alias": "Contents.Item.Desc.9101444",
        "text": "Essence used for the evolution of Flying Rifle. \\n When evolving, the Penetrating Power of Flying Rhythm is increased by 10%."
    },
    "99001359": {
        "deprecated": false,
        "Dev_Desc": "극한의 정수 : 용렬빙하 (각인)",
        "id": 99001359,
        "alias": "Contents.Item.Desc.9101445",
        "text": "Essence used for the evolution of glacial glaciers.\\nWhen evolving, there is a chance to additionally apply a slow effect."
    },
    "99001360": {
        "deprecated": false,
        "Dev_Desc": "돌파의 정수 : 용렬빙하 (각인)",
        "id": 99001360,
        "alias": "Contents.Item.Desc.9101446",
        "text": "Essence used for the evolution of Dragon Ridge Glacier. \\n When evolving, the range width of Dragon Ridge Glacier increases and hits up to 5 people within the range."
    },
    "99001361": {
        "deprecated": false,
        "Dev_Desc": "극한의 정수 : 봉황시 (각인)",
        "id": 99001361,
        "alias": "Contents.Item.Desc.9101447",
        "text": "Essence used to evolve the phoenix. \\n When evolving, the penetrating power of the phoenix is ​​increased by 20%."
    },
    "99001362": {
        "deprecated": false,
        "Dev_Desc": "돌파의 정수 : 봉황시 (각인)",
        "id": 99001362,
        "alias": "Contents.Item.Desc.9101448",
        "text": "Essence used to evolve the phoenix.\\nDamage increases when evolving.\\n\\n[Prerequisite]\\nEnhancement Level 9 or higher"
    },
    "99001363": {
        "deprecated": false,
        "Dev_Desc": "극한의 정수 : 화륜 (각인)",
        "id": 99001363,
        "alias": "Contents.Item.Desc.9101449",
        "text": "Essence used to evolve the Fire Ring. \\n Evolving reduces the cooldown of the Fire Ring by 20 seconds."
    },
    "99001364": {
        "deprecated": false,
        "Dev_Desc": "돌파의 정수 : 유성 (각인)",
        "id": 99001364,
        "alias": "Contents.Item.Desc.9101450",
        "text": "Essence used to evolve meteors.\\nWhen evolving, the meteor range increases, and the damage of the ice meteors increases.\\n\\n[Prerequisite]\\nEnhancement Level 9 or higher"
    },
    "99001365": {
        "deprecated": false,
        "Dev_Desc": "극한의 정수 : 비륜연휘 (각인)",
        "id": 99001365,
        "alias": "Contents.Item.Desc.9101451",
        "text": "Used to level up Scorching Shower.\nUses a combo technique that causes a massive explosion, which also affects the nearby enemies afflicted with Burn."
    },
    "99001366": {
        "deprecated": false,
        "Dev_Desc": "증폭의 정수 : 봉황시 (각인)",
        "id": 99001366,
        "alias": "Contents.Item.Desc.9101452",
        "text": "Used to level up Phoenix.\nAcquires Heater which boosts Attack Speed for a short period of time."
    },
    "99001367": {
        "deprecated": false,
        "Dev_Desc": "증폭의 정수 : 용렬빙하 (각인)",
        "id": 99001367,
        "alias": "Contents.Item.Desc.9101453",
        "text": "Used to level up Frosty Gimlet.\nIncreases its range and affects up to 5 enemies within range."
    },
    "99001368": {
        "deprecated": false,
        "Dev_Desc": "증폭의 정수 : 화륜 (각인)",
        "id": 99001368,
        "alias": "Contents.Item.Desc.9101454",
        "text": "Essence used to evolve the fire wheel. \\n When evolving, using the fire wheel increases attack speed by 30%."
    },
    "99001369": {
        "deprecated": false,
        "Dev_Desc": "돌파의 정수 : 화륜 (각인)",
        "id": 99001369,
        "alias": "Contents.Item.Desc.9101455",
        "text": "Essence used to evolve the Fire Ring.\\nUse the Fire Ring during evolution to increase the Soul Activation Rate by 5%.\\n\\n[Prerequisites]\\nEnhance Skill Level 9 or higher"
    },
    "99001375": {
        "deprecated": false,
        "Dev_Desc": "증폭의 정수 : 추적화살 (각인)",
        "id": 99001375,
        "alias": "Contents.Item.Desc.9101510",
        "text": "Essence used for the evolution of tracking arrows. \\nEvolution increases the damage of tracking arrows."
    },
    "99001376": {
        "deprecated": false,
        "Dev_Desc": "증폭의 정수 : 화살비 (각인)",
        "id": 99001376,
        "alias": "Contents.Item.Desc.9101511",
        "text": "Essence used to evolve Rain of Arrows. \\n When evolving, the damage of Rain of Arrows increases and hits up to 3 people within range."
    },
    "99001377": {
        "deprecated": false,
        "Dev_Desc": "증폭의 정수 : 출혈화살 (각인)",
        "id": 99001377,
        "alias": "Contents.Item.Desc.9101512",
        "text": "Essence used to evolve Bleeding Arrow. \\n Evolving reduces the cooldown of Bleeding Arrow by 1 second."
    },
    "99001378": {
        "deprecated": false,
        "Dev_Desc": "돌파의 정수 : 후퇴사격 (각인)",
        "id": 99001378,
        "alias": "Contents.Item.Desc.9101513",
        "text": "Essence used to evolve Retreat Shot.\\nWhen evolving, Evasion increases by 30 while using Retreat Shot.\\n\\n[Prerequisite]\\nLevel 9 or higher for Defense Enhancement"
    },
    "99001385": {
        "deprecated": false,
        "Dev_Desc": "극한의 정수 : 추적화살 (각인)",
        "id": 99001385,
        "alias": "Contents.Item.Desc.9101520",
        "text": "Used to level up Tracker.\nIncreases its damage and Ranged Critical Rate."
    },
    "99001386": {
        "deprecated": false,
        "Dev_Desc": "증폭의 정수 : 다발화살 (각인)",
        "id": 99001386,
        "alias": "Contents.Item.Desc.9101521",
        "text": "Used to level up Bundle Shot.\nInflicts Bleed on every Critical Hit."
    },
    "99001387": {
        "deprecated": false,
        "Dev_Desc": "증폭의 정수 : 다중사격 (각인)",
        "id": 99001387,
        "alias": "Contents.Item.Desc.9101522",
        "text": "Used to level up Multi Shot.\nInflicts Bleed on every Critical Hit."
    },
    "99001388": {
        "deprecated": false,
        "Dev_Desc": "극한의 정수 : 출혈화살 (각인)",
        "id": 99001388,
        "alias": "Contents.Item.Desc.9101523",
        "text": "Used to level up Bleeding Arrow.\nIncreases its Focus cost."
    },
    "99001389": {
        "deprecated": false,
        "Dev_Desc": "돌파의 정수 : 화살비 (각인)",
        "id": 99001389,
        "alias": "Contents.Item.Desc.9101524",
        "text": "Essence used to evolve the Rain of Arrows.\\nWhen evolving, there is a chance to apply the bleeding effect with every hit.\\n\\n[Prerequisite]\\nLevel 9 or above"
    },
    "99001395": {
        "deprecated": false,
        "Dev_Desc": "돌파의 정수 : 추적화살 (각인)",
        "id": 99001395,
        "alias": "Contents.Item.Desc.9101530",
        "text": "Used to level up Tracker.\nGreatly increases its damage and Ranged Critical Rate."
    },
    "99001396": {
        "deprecated": false,
        "Dev_Desc": "극한의 정수 : 화살비 (각인)",
        "id": 99001396,
        "alias": "Contents.Item.Desc.9101531",
        "text": "Used to level up Arrow Shower.\nInflicts Bleed on each strike."
    },
    "99001397": {
        "deprecated": false,
        "Dev_Desc": "극한의 정수 : 다중사격 (각인)",
        "id": 99001397,
        "alias": "Contents.Item.Desc.9101532",
        "text": "Used to level up Multi Shot.\nIncreases its damage and Ranged Critical Rate."
    },
    "99001398": {
        "deprecated": false,
        "Dev_Desc": "증폭의 정수 : 살상명령 (각인)",
        "id": 99001398,
        "alias": "Contents.Item.Desc.9101533",
        "text": "Used to level up Command to Kill.\nIncreases its duration."
    },
    "99001399": {
        "deprecated": false,
        "Dev_Desc": "돌파의 정수 : 출혈화살 (각인)",
        "id": 99001399,
        "alias": "Contents.Item.Desc.9101534",
        "text": "Used to level up Bleeding Arrow.\nIncreases its Critical Rate and stacks Bleed 2 times on Critical Hit."
    },
    "99001400": {
        "deprecated": false,
        "Dev_Desc": "돌파의 정수 : 살상명령 (각인)",
        "id": 99001400,
        "alias": "Contents.Item.Desc.9101535",
        "text": "Essence used to evolve the kill command.\\nWhen evolving, when using the kill command, additional critical attack damage increases by 7."
    },
    "99001401": {
        "deprecated": false,
        "Dev_Desc": "돌파의 정수 : 다중사격 (각인)",
        "id": 99001401,
        "alias": "Contents.Item.Desc.9101536",
        "text": "Essence used for the evolution of multi-shot.\\nWhen evolving, there is a certain probability of applying the bleeding effect to each critical hit."
    },
    "99001405": {
        "deprecated": false,
        "Dev_Desc": "극한의 정수 : 다발화살 (각인)",
        "id": 99001405,
        "alias": "Contents.Item.Desc.9101540",
        "text": "Used to level up Bundle Shot.\nIncreases its Ranged Critical Rate and casts Bundle Shot 2 times in a row."
    },
    "99001406": {
        "deprecated": false,
        "Dev_Desc": "극한의 정수 : 후퇴사격 (각인)",
        "id": 99001406,
        "alias": "Contents.Item.Desc.9101541",
        "text": "Used to level up Back Shot.\nHas a chance to push and inflict Stun on the enemy."
    },
    "99001407": {
        "deprecated": false,
        "Dev_Desc": "돌파의 정수 : 다중사격 (각인)",
        "id": 99001407,
        "alias": "Contents.Item.Desc.9101542",
        "text": "Used to level up Multi Shot.\nGreatly increases its damage and Ranged Critical Rate."
    },
    "99001408": {
        "deprecated": false,
        "Dev_Desc": "증폭의 정수 : 조준사격 (각인)",
        "id": 99001408,
        "alias": "Contents.Item.Desc.9101543",
        "text": "Used to level up Aimed Shot.\nInflicts Bleed at max stacks on Critical Hit."
    },
    "99001409": {
        "deprecated": false,
        "Dev_Desc": "증폭의 정수 : 후퇴사격 (각인)",
        "id": 99001409,
        "alias": "Contents.Item.Desc.9101544",
        "text": "Used to level up Back Shot.\nHas a chance to inflict Petrify on the enemy."
    },
    "99001410": {
        "deprecated": false,
        "Dev_Desc": "극한의 정수 : 살상명령 (각인)",
        "id": 99001410,
        "alias": "Contents.Item.Desc.9101545",
        "text": "Used to level up Command to Kill.\nIncreases its Critical Bonus."
    },
    "99001411": {
        "deprecated": false,
        "Dev_Desc": "극한의 정수 : 조준사격 (각인)",
        "id": 99001411,
        "alias": "Contents.Item.Desc.9101546",
        "text": "Essence used to evolve Aimed Shot. \\n Evolving increases the ranged critical rate by 50% while using Aimed Shot."
    },
    "99001412": {
        "deprecated": false,
        "Dev_Desc": "극한의 정수 : 반마화살 (각인)",
        "id": 99001412,
        "alias": "Contents.Item.Desc.9101547",
        "text": "Essence used for the evolution of anti-magical arrows. \\n During evolution, targets hit by anti-magic arrows cannot receive effects up to [Extreme] protection for 10 seconds."
    },
    "99001413": {
        "deprecated": false,
        "Dev_Desc": "돌파의 정수 : 반마화살 (각인)",
        "id": 99001413,
        "alias": "Contents.Item.Desc.9101548",
        "text": "Essence used for the evolution of Anti-Magic Arrows. \\n When evolving, up to [Breaking] protection is possible, and targets hit by Anti-Magic Arrows cannot receive the effect until [Breaking] Protection for 10 seconds."
    },
    "99001414": {
        "deprecated": false,
        "Dev_Desc": "돌파의 정수 : 조준사격 (각인)",
        "id": 99001414,
        "alias": "Contents.Item.Desc.9101549",
        "text": "Essence used to evolve Aimed Shot.\\nWhen evolved, Aimed Shot has a chance to penetrate the block and apply the Stun effect."
    },
    "99001415": {
        "deprecated": false,
        "Dev_Desc": "돌파의 정수 : 다발화살 (각인)",
        "id": 99001415,
        "alias": "Contents.Item.Desc.9101550",
        "text": "Used to level up Bundle Shot.\nGreatly increases its Ranged Critical Rate and casts Bundle Shot 3 times in a row."
    },
    "99001416": {
        "deprecated": false,
        "Dev_Desc": "증폭의 정수 : 반마화살 (각인)",
        "id": 99001416,
        "alias": "Contents.Item.Desc.9101551",
        "text": "Used to level up Magic Arrow.\nUpon an accurate hit, it disables Guardian for 10 seconds."
    },
    "99001417": {
        "deprecated": false,
        "Dev_Desc": "증폭의 정수: 봉쇄화살",
        "id": 99001417,
        "alias": "Contents.Item.Desc.9101552",
        "text": "\"봉쇄화살\"의 진화에 사용되는 정수입니다.\n진화 시 \"봉쇄화살\" 범위 내 대상의 회피가 10 감소합니다."
    },
    "99001418": {
        "deprecated": false,
        "Dev_Desc": "극한의 정수: 봉쇄화살",
        "id": 99001418,
        "alias": "Contents.Item.Desc.9101553",
        "text": "\"봉쇄화살\"의 진화에 사용되는 정수입니다.\n진화 시 \"봉쇄화살\" 범위 내 대상의 통제 저항률이 5% 감소합니다."
    },
    "99001419": {
        "deprecated": false,
        "Dev_Desc": "돌파의 정수: 봉쇄화살",
        "id": 99001419,
        "alias": "Contents.Item.Desc.9101554",
        "text": "\"봉쇄화살\"의 진화에 사용되는 정수입니다.\n진화 시 대상을 중심으로 당기기 효과가 적용되며, 이동 속도 감소율이 추가로 증가합니다.\n\n[선행 조건]\n무공 강화 단계 +9 이상"
    },
    "99001426": {
        "deprecated": false,
        "Dev_Desc": "증폭의 정수 : 연섬뢰 (각인)",
        "id": 99001426,
        "alias": "Contents.Item.Desc.9101610",
        "text": "Used to level up Avenging Blow.\nDecreases its Focus cost."
    },
    "99001427": {
        "deprecated": false,
        "Dev_Desc": "증폭의 정수 : 강섬뢰 (각인)",
        "id": 99001427,
        "alias": "Contents.Item.Desc.9101611",
        "text": "Used to level up Avenging Ray.\nDecreases its cooldown."
    },
    "99001428": {
        "deprecated": false,
        "Dev_Desc": "증폭의 정수 : 생령치유 (각인)",
        "id": 99001428,
        "alias": "Contents.Item.Desc.9101612",
        "text": "Essence used for the evolution of Spirit Healing. \\n When evolving, the cooldown of Spirit Heal is reduced by 2 seconds."
    },
    "99001436": {
        "deprecated": false,
        "Dev_Desc": "극한의 정수 : 연섬뢰 (각인)",
        "id": 99001436,
        "alias": "Contents.Item.Desc.9101620",
        "text": "Used to level up Avenging Blow.\nDecreases its cooldown."
    },
    "99001437": {
        "deprecated": false,
        "Dev_Desc": "극한의 정수 : 강섬뢰 (각인)",
        "id": 99001437,
        "alias": "Contents.Item.Desc.9101621",
        "text": "Used to level up Avenging Ray.\nDecreases its Accuracy Chance."
    },
    "99001438": {
        "deprecated": false,
        "Dev_Desc": "증폭의 정수 : 생령합일 (각인)",
        "id": 99001438,
        "alias": "Contents.Item.Desc.9101622",
        "text": "Essence used for the evolution of Unity of Life. \\n When evolving, the energy consumption of Unity of Life is reduced by 50."
    },
    "99001439": {
        "deprecated": false,
        "Dev_Desc": "증폭의 정수 : 심기일전 (각인)",
        "id": 99001439,
        "alias": "Contents.Item.Desc.9101623",
        "text": "Used to level up New Leaf.\nHas a chance to increase the party's Accuracy."
    },
    "99001446": {
        "deprecated": false,
        "Dev_Desc": "돌파의 정수 : 연섬뢰 (각인)",
        "id": 99001446,
        "alias": "Contents.Item.Desc.9101630",
        "text": "Essence used to evolve the Firefly.\\nWhen evolving, the fatality rate of the Firefly increases by 20%.\\n\\n[Prerequisites]\\nLevel 9 or higher to enhance the firepower"
    },
    "99001447": {
        "deprecated": false,
        "Dev_Desc": "돌파의 정수 : 강섬뢰 (각인)",
        "id": 99001447,
        "alias": "Contents.Item.Desc.9101631",
        "text": "Essence used to evolve the Lightning Lightning.\\nWhen evolving, the damage increases in proportion to the healing power.\\n\\n[Prerequisite]\\nLevel 9 or higher to enhance defenseless power"
    },
    "99001448": {
        "deprecated": false,
        "Dev_Desc": "극한의 정수 : 생령치유 (각인)",
        "id": 99001448,
        "alias": "Contents.Item.Desc.9101632",
        "text": "Essence used for the evolution of Spirit Healing. \\n Chance to heal the target twice."
    },
    "99001449": {
        "deprecated": false,
        "Dev_Desc": "극한의 정수 : 심기일전 (각인)",
        "id": 99001449,
        "alias": "Contents.Item.Desc.9101633",
        "text": "Used to level up New Leaf.\nIncreases its duration."
    },
    "99001450": {
        "deprecated": false,
        "Dev_Desc": "극한의 정수 : 생령합일 (각인)",
        "id": 99001450,
        "alias": "Contents.Item.Desc.9101634",
        "text": "Essence used for the evolution of Unity of Life. \\nEvolution reduces the cooldown of Unity of Life by 2 seconds."
    },
    "99001451": {
        "deprecated": false,
        "Dev_Desc": "극한의 정수 : 청화 (각인)",
        "id": 99001451,
        "alias": "Contents.Item.Desc.9101635",
        "text": "Essence used to evolve blue flowers. \\nEvolution increases the damage of blue flowers."
    },
    "99001452": {
        "deprecated": false,
        "Dev_Desc": "돌파의 정수 : 치유지대 (각인)",
        "id": 99001452,
        "alias": "Contents.Item.Desc.9101636",
        "text": "Essence used to evolve the Healing Squad.\\nWhen evolving, the target's critical resistance is increased by 20%.\\n\\n[Prerequisite]\\nEnhancement Level 9 or higher"
    },
    "99001453": {
        "deprecated": false,
        "Dev_Desc": "돌파의 정수 : 청화 (각인)",
        "id": 99001453,
        "alias": "Contents.Item.Desc.9101637",
        "text": "Essence used for the evolution of blue and white.\\nWhen evolving, the probability of removal of history is increased and the cooldown is reduced by 3 seconds."
    },
    "99001456": {
        "deprecated": false,
        "Dev_Desc": "증폭의 정수 : 구원 (각인)",
        "id": 99001456,
        "alias": "Contents.Item.Desc.9101640",
        "text": "Used to level up Redemption.\nDecreases its cooldown."
    },
    "99001457": {
        "deprecated": false,
        "Dev_Desc": "돌파의 정수 : 생령치유 (각인)",
        "id": 99001457,
        "alias": "Contents.Item.Desc.9101641",
        "text": "Essence used for the evolution of healing spirits.\\nWhen evolving, heals up to 4 nearby party members in succession, with a higher chance of healing the target twice."
    },
    "99001458": {
        "deprecated": false,
        "Dev_Desc": "증폭의 정수 : 치유지대 (각인)",
        "id": 99001458,
        "alias": "Contents.Item.Desc.9101642",
        "text": "Essence used to evolve the healing zone. \\nEvolving reduces the cooldown of the healing zone by 5 seconds."
    },
    "99001459": {
        "deprecated": false,
        "Dev_Desc": "증폭의 정수 : 청화 (각인)",
        "id": 99001459,
        "alias": "Contents.Item.Desc.9101643",
        "text": "Used to level up Cobalt Blossom.\nDecreases its damage relative to Heal."
    },
    "99001460": {
        "deprecated": false,
        "Dev_Desc": "돌파의 정수 : 생령합일 (각인)",
        "id": 99001460,
        "alias": "Contents.Item.Desc.9101644",
        "text": "Essence used for the evolution of unity of living spirits. \\nIn evolution, the movement speed of the united state is greatly increased."
    },
    "99001461": {
        "deprecated": false,
        "Dev_Desc": "극한의 정수 : 심판 (각인)",
        "id": 99001461,
        "alias": "Contents.Item.Desc.9101645",
        "text": "Essence used to evolve Judgment. When evolving, damage increases in proportion to healing power."
    },
    "99001462": {
        "deprecated": false,
        "Dev_Desc": "돌파의 정수 : 심판 (각인)",
        "id": 99001462,
        "alias": "Contents.Item.Desc.9101646",
        "text": "Essence used to evolve Judgment.\\nWhen evolving, there is a chance to apply Stun effect.\\n\\n[Prerequisite]\\nEnhancement Level 9 or higher"
    },
    "99001463": {
        "deprecated": false,
        "Dev_Desc": "극한의 정수 : 수호 (각인)",
        "id": 99001463,
        "alias": "Contents.Item.Desc.9101647",
        "text": "Essence used to evolve the guardian.\\nWhen evolving, the damage reduction value of the guardian is increased by 5%, and the range of the guardian is increased."
    },
    "99001464": {
        "deprecated": false,
        "Dev_Desc": "돌파의 정수 : 수호 (각인)",
        "id": 99001464,
        "alias": "Contents.Item.Desc.9101648",
        "text": "Used to level up Guardian.\nIncreases its Damage Down effect and nullifies the removal of Magic Arrow."
    },
    "99001465": {
        "deprecated": false,
        "Dev_Desc": "극한의 정수 : 구원 (각인)",
        "id": 99001465,
        "alias": "Contents.Item.Desc.9101649",
        "text": "Essence used to evolve salvation. \\nEvolution reduces the cooldown of salvation by 10 seconds."
    },
    "99001466": {
        "deprecated": false,
        "Dev_Desc": "증폭의 정수 : 심판 (각인)",
        "id": 99001466,
        "alias": "Contents.Item.Desc.9101650",
        "text": "Used to level up Judgment.\nUpon accurate hit, heals the allies around the target."
    },
    "99001467": {
        "deprecated": false,
        "Dev_Desc": "돌파의 정수 : 심기일전 (각인)",
        "id": 99001467,
        "alias": "Contents.Item.Desc.9101651",
        "text": "Essence used for the evolution of the battlefield.\\nThere is a chance to increase weapon damage by 7 when used.\\n\\n[Prerequisite]\\nEnhancement Level 9 or higher"
    },
    "99001468": {
        "deprecated": false,
        "Dev_Desc": "극한의 정수 : 치유지대 (각인)",
        "id": 99001468,
        "alias": "Contents.Item.Desc.9101652",
        "text": "Essence used to evolve the Healing Zone. \\n Evolving increases the duration of the Healing Zone by 3 seconds."
    },
    "99001469": {
        "deprecated": false,
        "Dev_Desc": "증폭의 정수 : 수호 (각인)",
        "id": 99001469,
        "alias": "Contents.Item.Desc.9101653",
        "text": "Used to level up Guardian.\nIncreases its Damage Down effect and nullifies the removal of Magic Arrow."
    },
    "99001470": {
        "deprecated": false,
        "Dev_Desc": "돌파의 정수 : 구원 (각인)",
        "id": 99001470,
        "alias": "Contents.Item.Desc.9101654",
        "text": "Used to level up Redemption.\nAdditionally removes Airborne, Provoke, Burn, and Bleed effects."
    },
    "99002654": {
        "deprecated": false,
        "Dev_Desc": "봉쇄화살 / 액티브",
        "id": 99002654,
        "alias": "Contents.Item.Desc.9100544",
        "text": "특수한 화살을 날려 대상을 포함한 최대 3인에게 피해를 입히고, 일정 확률로 막기를 관통하여 기절시킵니다.\n범위 내 무공에 적중당한 대상은 구르기를 포함한 지면에서 발이 떨어지는 무공을 사용할 수 없으며, 귀환이 불가하고 이동 속도가 감소합니다."
    }
}