{
    "36001000": {
        "deprecated": false,
        "Dev_Desc": "하초",
        "id": 36001000,
        "alias": "MonsterGossip.36001000",
        "text": "是你吗.杀死我的同伴们！"
    },
    "36001001": {
        "deprecated": false,
        "Dev_Desc": "하초",
        "id": 36001001,
        "alias": "MonsterGossip.36001001",
        "text": "你这小子真是没礼貌.可笑！！"
    },
    "36001002": {
        "deprecated": false,
        "Dev_Desc": "하초",
        "id": 36001002,
        "alias": "MonsterGossip.36001002",
        "text": "我不像现在的孩子那么懦弱.说不懦弱..."
    },
    "36001003": {
        "deprecated": false,
        "Dev_Desc": "대와",
        "id": 36001003,
        "alias": "MonsterGossip.36001003",
        "text": "你回后面去打尾巴的河秀."
    },
    "36001004": {
        "deprecated": false,
        "Dev_Desc": "대와",
        "id": 36001004,
        "alias": "MonsterGossip.36001004",
        "text": "你的弱点是下巴和尾巴.破坏那个地方保守和！"
    },
    "36001005": {
        "deprecated": false,
        "Dev_Desc": "대와",
        "id": 36001005,
        "alias": "MonsterGossip.36001005",
        "text": "哎哟大傻瓜."
    },
    "36001006": {
        "deprecated": false,
        "Dev_Desc": "대와",
        "id": 36001006,
        "alias": "MonsterGossip.36001006",
        "text": "现在我也老了吗报酬来吧！哎哟，腰围！"
    },
    "36001007": {
        "deprecated": false,
        "Dev_Desc": "꼬와",
        "id": 36001007,
        "alias": "MonsterGossip.36001007",
        "text": "这里就是你的弱点伊秀."
    },
    "36001008": {
        "deprecated": false,
        "Dev_Desc": "꼬와",
        "id": 36001008,
        "alias": "MonsterGossip.36001008",
        "text": "我比理惠好多了"
    },
    "36001009": {
        "deprecated": false,
        "Dev_Desc": "리와",
        "id": 36001009,
        "alias": "MonsterGossip.36001009",
        "text": "这家伙的弱点是这里."
    },
    "36001010": {
        "deprecated": false,
        "Dev_Desc": "리와",
        "id": 36001010,
        "alias": "MonsterGossip.36001010",
        "text": "我比你强秀哇."
    },
    "36001011": {
        "deprecated": false,
        "Dev_Desc": "큰산",
        "id": 36001011,
        "alias": "MonsterGossip.36001011",
        "text": "你这家伙.①把头发弄碎！"
    },
    "36001012": {
        "deprecated": false,
        "Dev_Desc": "큰산",
        "id": 36001012,
        "alias": "MonsterGossip.36001012",
        "text": "我是大山！翻山越岭！①你这家伙也过不了这里！"
    },
    "36001013": {
        "deprecated": false,
        "Dev_Desc": "큰산",
        "id": 36001013,
        "alias": "MonsterGossip.36001013",
        "text": "利益还差得远呢！"
    },
    "36001014": {
        "deprecated": false,
        "Dev_Desc": "큰산",
        "id": 36001014,
        "alias": "MonsterGossip.36001014",
        "text": "竟敢.竟敢把这座大山…."
    },
    "36002000": {
        "deprecated": false,
        "Dev_Desc": "해룡의 사체_포트케일",
        "id": 36002000,
        "alias": "MonsterGossip.36002000",
        "text": "是谁.为什么妨碍我."
    },
    "36002001": {
        "deprecated": false,
        "Dev_Desc": "해룡의 사체_포트케일",
        "id": 36002001,
        "alias": "MonsterGossip.36002001",
        "text": "这个 宝石. 是我的！ 至死 对你来说. 池子 给你."
    },
    "36002002": {
        "deprecated": false,
        "Dev_Desc": "해룡의 사체_포트케일",
        "id": 36002002,
        "alias": "MonsterGossip.36002002",
        "text": "来.来等一下. 在这里. 死后 当然. 不~！！"
    },
    "36002003": {
        "deprecated": false,
        "Dev_Desc": "에레다 수장 하름",
        "id": 36002003,
        "alias": "MonsterGossip.36002003",
        "text": "像老鼠一样躲起来找什么来着？"
    },
    "36002004": {
        "deprecated": false,
        "Dev_Desc": "에레다 수장 하름",
        "id": 36002004,
        "alias": "MonsterGossip.36002004",
        "text": "你到底想什么."
    },
    "36002005": {
        "deprecated": false,
        "Dev_Desc": "에레다 수장 하름",
        "id": 36002005,
        "alias": "MonsterGossip.36002005",
        "text": "西路的轮回去哪儿了？"
    },
    "36002006": {
        "deprecated": false,
        "Dev_Desc": "에레다 수장 하름",
        "id": 36002006,
        "alias": "MonsterGossip.36002006",
        "text": "呵呵不错啊..."
    },
    "36002007": {
        "deprecated": false,
        "Dev_Desc": "에레다 수장 하름",
        "id": 36002007,
        "alias": "MonsterGossip.36002007",
        "text": "不会如愿的！"
    },
    "36002008": {
        "deprecated": false,
        "Dev_Desc": "에레다 수장 하름",
        "id": 36002008,
        "alias": "MonsterGossip.36002008",
        "text": "从深渊的缝隙..."
    },
    "36002009": {
        "deprecated": false,
        "Dev_Desc": "제 3기수 하름",
        "id": 36002009,
        "alias": "MonsterGossip.36002009",
        "text": "去死吧.臭小子."
    },
    "36002010": {
        "deprecated": false,
        "Dev_Desc": "제 3기수 하름",
        "id": 36002010,
        "alias": "MonsterGossip.36002010",
        "text": "全部杀掉！"
    },
    "36002011": {
        "deprecated": false,
        "Dev_Desc": "제 3기수 하름",
        "id": 36002011,
        "alias": "MonsterGossip.36002011",
        "text": "看看真正的力量！"
    },
    "36002012": {
        "deprecated": false,
        "Dev_Desc": "제 3기수 하름",
        "id": 36002012,
        "alias": "MonsterGossip.36002012",
        "text": "哦，为什么我被挤在后面！？"
    },
    "36002013": {
        "deprecated": false,
        "Dev_Desc": "제 3기수 하름",
        "id": 36002013,
        "alias": "MonsterGossip.36002013",
        "text": "那个.尼鲁大人..."
    },
    "36002014": {
        "deprecated": false,
        "Dev_Desc": "에레다 대장 오름",
        "id": 36002014,
        "alias": "MonsterGossip.36002014",
        "text": "你这是在做什么."
    },
    "36002015": {
        "deprecated": false,
        "Dev_Desc": "에레다 대장 오름",
        "id": 36002015,
        "alias": "MonsterGossip.36002015",
        "text": "住手."
    },
    "36002016": {
        "deprecated": false,
        "Dev_Desc": "에레다 대장 오름",
        "id": 36002016,
        "alias": "MonsterGossip.36002016",
        "text": "你到底想要什么."
    },
    "36002017": {
        "deprecated": false,
        "Dev_Desc": "아랑",
        "id": 36002017,
        "alias": "MonsterGossip.36002017",
        "text": "是认真做的吗？①为什么不能像那时候那样做呢？"
    },
    "36002018": {
        "deprecated": false,
        "Dev_Desc": "아랑",
        "id": 36002018,
        "alias": "MonsterGossip.36002018",
        "text": "等一下.不能再这样下去了."
    },
    "36002019": {
        "deprecated": false,
        "Dev_Desc": "운반해",
        "id": 36002019,
        "alias": "MonsterGossip.36002019",
        "text": "你这是怎么了.①你又是什么人！？"
    },
    "36002020": {
        "deprecated": false,
        "Dev_Desc": "운반해",
        "id": 36002020,
        "alias": "MonsterGossip.36002020",
        "text": "是梅花团派来的吗."
    },
    "36002021": {
        "deprecated": false,
        "Dev_Desc": "운반해",
        "id": 36002021,
        "alias": "MonsterGossip.36002021",
        "text": "等等.①那里！救了那家伙！"
    },
    "36002022": {
        "deprecated": false,
        "Dev_Desc": "운반해",
        "id": 36002022,
        "alias": "MonsterGossip.36002022",
        "text": "就算放了也…"
    },
    "36002023": {
        "deprecated": false,
        "Dev_Desc": "아랑",
        "id": 36002023,
        "alias": "MonsterGossip.36002023",
        "text": "啊，袭击！①小心！"
    },
    "36003000": {
        "deprecated": false,
        "Dev_Desc": "홍돈칠",
        "id": 36003000,
        "alias": "MonsterGossip.36003000",
        "text": "这种程度根本不可能~！"
    },
    "36003001": {
        "deprecated": false,
        "Dev_Desc": "홍돈칠",
        "id": 36003001,
        "alias": "MonsterGossip.36003001",
        "text": "要妨碍的话就退出吧~！"
    },
    "36003002": {
        "deprecated": false,
        "Dev_Desc": "홍돈팔",
        "id": 36003002,
        "alias": "MonsterGossip.36003002",
        "text": "你这是在做什么."
    },
    "36003003": {
        "deprecated": false,
        "Dev_Desc": "홍돈팔",
        "id": 36003003,
        "alias": "MonsterGossip.36003003",
        "text": "身体没有力气..."
    },
    "36003004": {
        "deprecated": false,
        "Dev_Desc": "아랑",
        "id": 36003004,
        "alias": "MonsterGossip.36003004",
        "text": "要用真心攻击！"
    },
    "36003005": {
        "deprecated": false,
        "Dev_Desc": "아랑",
        "id": 36003005,
        "alias": "MonsterGossip.36003005",
        "text": "嗯.好像可以啊！？"
    },
    "36003006": {
        "deprecated": false,
        "Dev_Desc": "검은새벽단 강우",
        "id": 36003006,
        "alias": "MonsterGossip.36003006",
        "text": "你是谁.竟然胆敢来这里.我会让你后悔的."
    },
    "36003007": {
        "deprecated": false,
        "Dev_Desc": "검은새벽단 강우",
        "id": 36003007,
        "alias": "MonsterGossip.36003007",
        "text": "他和我在一起！"
    },
    "36003008": {
        "deprecated": false,
        "Dev_Desc": "검은새벽단 강우",
        "id": 36003008,
        "alias": "MonsterGossip.36003008",
        "text": "我要杀了你献给他！"
    },
    "36003009": {
        "deprecated": false,
        "Dev_Desc": "검은새벽단 강우",
        "id": 36003009,
        "alias": "MonsterGossip.36003009",
        "text": "不行！！"
    },
    "36003010": {
        "deprecated": false,
        "Dev_Desc": "염환",
        "id": 36003010,
        "alias": "MonsterGossip.36003010",
        "text": "你又是什么家伙."
    },
    "36003011": {
        "deprecated": false,
        "Dev_Desc": "염환",
        "id": 36003011,
        "alias": "MonsterGossip.36003011",
        "text": "这股力量！？"
    },
    "36003012": {
        "deprecated": false,
        "Dev_Desc": "염환",
        "id": 36003012,
        "alias": "MonsterGossip.36003012",
        "text": "献给他吧！"
    },
    "36003013": {
        "deprecated": false,
        "Dev_Desc": "염환",
        "id": 36003013,
        "alias": "MonsterGossip.36003013",
        "text": "返回深渊…"
    },
    "36005000": {
        "deprecated": false,
        "id": 36005000,
        "alias": "MonsterGossip.36005000",
        "text": "冤枉啊.如果还有开发治疗药的时间的话..."
    },
    "36005001": {
        "deprecated": false,
        "id": 36005001,
        "alias": "MonsterGossip.36005001",
        "text": "身体大是罪吗.我是怪物吗！"
    },
    "36005002": {
        "deprecated": false,
        "id": 36005002,
        "alias": "MonsterGossip.36005002",
        "text": "不要再抱怨了."
    },
    "36005003": {
        "deprecated": false,
        "id": 36005003,
        "alias": "MonsterGossip.36005003",
        "text": "现在已经厌倦了长臂猿这个绰号."
    },
    "36001015": {
        "deprecated": false,
        "Dev_Desc": "반달호수_의문의 사내",
        "id": 36001015,
        "alias": "MonsterGossip.36001015",
        "text": "不要妨碍我！①妨碍的话真的会打！！"
    },
    "36001016": {
        "deprecated": false,
        "Dev_Desc": "반달호수_의문의 사내",
        "id": 36001016,
        "alias": "MonsterGossip.36001016",
        "text": "住手住手.错了…①我也有苦衷！"
    },
    "36001017": {
        "deprecated": false,
        "Dev_Desc": "반달호수_위험해 보이는 자",
        "id": 36001017,
        "alias": "MonsterGossip.36001017",
        "text": "不能放过目击者！死吧！嘻嘻！！！"
    },
    "36001018": {
        "deprecated": false,
        "Dev_Desc": "반달호수_위험해 보이는 자",
        "id": 36001018,
        "alias": "MonsterGossip.36001018",
        "text": "来，等一下，这些都是①任延秀让我做的…！"
    },
    "36001019": {
        "deprecated": false,
        "Dev_Desc": "반달호수_치연",
        "id": 36001019,
        "alias": "MonsterGossip.36001019",
        "text": "来，发挥一下实力吧！"
    },
    "36001020": {
        "deprecated": false,
        "Dev_Desc": "반달호수_치연",
        "id": 36001020,
        "alias": "MonsterGossip.36001020",
        "text": "不错啊."
    },
    "36001021": {
        "deprecated": false,
        "Dev_Desc": "반달호수_청인족 해적단",
        "id": 36001021,
        "alias": "MonsterGossip.36001021",
        "text": "这又是干什么的？！"
    },
    "36001022": {
        "deprecated": false,
        "Dev_Desc": "반달호수_대어방 자경단",
        "id": 36001022,
        "alias": "MonsterGossip.36001022",
        "text": "别插嘴，快老实回去吧！"
    },
    "36001023": {
        "deprecated": false,
        "Dev_Desc": "반달호수_임연수의 용병",
        "id": 36001023,
        "alias": "MonsterGossip.36001023",
        "text": "你是谁.你怎么来了."
    },
    "36001024": {
        "deprecated": false,
        "Dev_Desc": "반달호수_깨어난 수호자 거석장군",
        "id": 36001024,
        "alias": "MonsterGossip.36001024",
        "text": "谁妨碍我的睡眠啊呜呜…"
    }
}