{
    "11020000": {
        "deprecated": false,
        "Dev_Desc": "2막 1장",
        "id": 11020000,
        "alias": "Contents.Quest.Desc.20000",
        "text": "还没有公开的故事"
    },
    "11020001": {
        "deprecated": false,
        "Dev_Desc": "2막 2장",
        "id": 11020001,
        "alias": "Contents.Quest.Desc.20001",
        "text": "还没有公开的故事"
    },
    "11020002": {
        "deprecated": false,
        "Dev_Desc": "2막 3장",
        "id": 11020002,
        "alias": "Contents.Quest.Desc.20002",
        "text": "还没有公开的故事"
    },
    "11020003": {
        "deprecated": false,
        "Dev_Desc": "2막 6장",
        "id": 11020003,
        "alias": "Contents.Quest.Desc.20003",
        "text": "还没有公开的故事"
    },
    "11020004": {
        "deprecated": false,
        "Dev_Desc": "2막 7장",
        "id": 11020004,
        "alias": "Contents.Quest.Desc.20004",
        "text": "还没有公开的故事"
    },
    "11020005": {
        "deprecated": false,
        "Dev_Desc": "2막 8장",
        "id": 11020005,
        "alias": "Contents.Quest.Desc.20005",
        "text": "还没有公开的故事"
    },
    "11020006": {
        "deprecated": false,
        "Dev_Desc": "2막 9장",
        "id": 11020006,
        "alias": "Contents.Quest.Desc.20006",
        "text": "还没有公开的故事"
    },
    "11020007": {
        "deprecated": false,
        "Dev_Desc": "2막 1장",
        "id": 11020007,
        "alias": "Contents.Quest.Desc.20007",
        "text": "为了寻找消失的哈姆和肥沃，决定和阿郎一起去海月大陆。但是从港口开始气氛就不寻常…？\n\n为了寻找哈姆，应该从寻找埃莱达开始一步一步地开始。去附近找找埃莱达。"
    },
    "11020008": {
        "deprecated": false,
        "Dev_Desc": "2막 2장",
        "id": 11020008,
        "alias": "Contents.Quest.Desc.20008",
        "text": "虽然坚决拒绝攀登，但我们必须进行祭祀。埃莱达会不会答应你的协助，以后再考虑吧。\n\n首先要收集有关祭祀的信息。看来可以从与祭祀最为密切的巴隆族那里获得祭祀的情报。\n\n在据点周围寻找巴隆族。"
    },
    "11020009": {
        "deprecated": false,
        "Dev_Desc": "2막 3장",
        "id": 11020009,
        "alias": "Contents.Quest.Desc.20009",
        "text": "首阳成功拿到祭祀许可证。去见社豪的首长们，听取他们的请求，接受祭祀材料。"
    },
    "11020010": {
        "deprecated": false,
        "Dev_Desc": "2막 6장",
        "id": 11020010,
        "alias": "Contents.Quest.Desc.20010",
        "text": "拿到许可证材料都收集好了。不知道去埃莱达秘密据点的路…！\n\n想想半月湖上发生的事情，如果是英教员总长弗朗弗朗弗朗弗朗弗朗弗朗弗朗弗朗弗朗的话，应该可以把它建设成埃莱达秘密据点吧…？\n\n快点找一下紫色吧。"
    },
    "11020011": {
        "deprecated": false,
        "Dev_Desc": "2막 7장",
        "id": 11020011,
        "alias": "Contents.Quest.Desc.20011",
        "text": "果然能按照阿郎的想法出来，通过阿郎将埃莱达秘密据点建造起来吗…？为什么每次都要挑战这么鲁莽的事情！？\n\n不知道是否知道这颗心，弗朗弗朗弗朗用坚定的表情等着我们。相信总长前往埃莱达秘密据点。"
    },
    "11020012": {
        "deprecated": false,
        "Dev_Desc": "2막 8장",
        "id": 11020012,
        "alias": "Contents.Quest.Desc.20012",
        "text": "经过迂回曲折，终于遇到了神兽派，但事情并没有按照计划解决。\n\n暂时冷静一下头脑。找一个可以在周围安静思考的地方。"
    },
    "11020013": {
        "deprecated": false,
        "Dev_Desc": "2막 9장",
        "id": 11020013,
        "alias": "Contents.Quest.Desc.20013",
        "text": "开裂引水失败。\n为了得到肥沃而前往风白门的阿郎。虽然可以从出身门派得到帮助，但是阿郎的自信心太过了…！\n\n和阿郎一起走向风白门吧。"
    },
    "11020014": {
        "deprecated": false,
        "Dev_Desc": "2막 1장",
        "id": 11020014,
        "alias": "Contents.Quest.Desc.20014",
        "text": "到达海月大陆的礼都港后，我们从一开始就无法避免居民们的警戒视线。因为我们毁了半月湖武术大赛的传闻已经传到了这里。但是也有可以涌出的漏洞！为了给居民们提供必要的蜘蛛网，可以获得有关埃莱达的情报。\n\n得知有埃莱达的情报后，一到东部生态调查林，我们就被埃莱达门派成员突袭。我们在那里遇到了埃莱达部门的波澜。\n\n奥姆一看到我们就生气地说：攻击文主还不够，还间谍吗？难道河明还是文主吗。光是祭祀我们的目的派萨就已经很吃力了，还要查明哈姆的真实身份…我们能做好吧？"
    },
    "11020015": {
        "deprecated": false,
        "Dev_Desc": "2막 2장",
        "id": 11020015,
        "alias": "Contents.Quest.Desc.20015",
        "text": "阿郎和英教员的巴隆虽然发生了小事故（？），但是从巴隆那里获得了祭祀神的“天神祭礼”的情报。\n天神祭礼需要叫路的铃铛、照路的镜子、筑路的剑，这三种东西分别可以从梅花团、桃花像殿、金嘤铁门中获得。幸运的是，在半月湖上有一个得分给了沙湖，只要好好说话，应该能借到吧？\n\n除了这三件东西外，还需要国家的许可，所以去了海月大陆接受国家权限的修养。因为没有一面之识，不能直接和队长对话，所以只能听从首阳队员们的委托，才能单独对待首阳的队长、西钟文。\n\n首阳大将西钟文给了许可证，没有想象中那么难。他给了许可证，并吐露了不满：火魔扰乱了世界，神兽在做什么。他的话也有道理。如果叫信秀出来我就要问你。"
    },
    "11020016": {
        "deprecated": false,
        "Dev_Desc": "2막 3장",
        "id": 11020016,
        "alias": "Contents.Quest.Desc.20016",
        "text": "收集三种材料的第一步，我为了得到叫路的铃铛梅花灵，听从了红梅团长的请求。\n\n请求释放被血雨牌绑架的新团员，原来是为了利用我牵制血雨牌势力。理由是，如果梅花团直接介入，有可能演变成两个势力的战斗。虽然是有道理的话但是无法抹去被利用的感觉..。不过，既然能收到梅花令，那也没关系！\n\n现在还剩下制作道路的剑、照亮道路的铃铛两种材料。寻找剩下的沙湖\n寻找材料。"
    },
    "11020017": {
        "deprecated": false,
        "Dev_Desc": "2막 6장",
        "id": 11020017,
        "alias": "Contents.Quest.Desc.20017",
        "text": "仔细一想，我们不知道去埃莱达秘密据点的方法，决定与英教员的校长、弗朗弗朗弗朗见面寻求帮助。在雾林开拓地寻找弗朗弗朗的瞬间！我们在半月湖见到了英老师的东洞。但不知是什么偶然，在那里救了一个处于困境的巴隆，那就是巴隆的孙子！于是，我们在小巴隆的引导下，见到了英教员总长弗朗弗朗弗朗弗朗弗朗弗朗弗朗。听到那句话，阿郎毫不犹豫地和我指了指自己。我们确实去过，但这有什么鲁莽的？！虽然说没有做过活着的存在..。我只能相信你。"
    },
    "11020018": {
        "deprecated": false,
        "Dev_Desc": "2막 7장",
        "id": 11020018,
        "alias": "Contents.Quest.Desc.20018",
        "text": "到达埃莱达秘密据点后，阿郎只留下不知道的话就消失了。一个人走进哈姆的办公室时，从背后传来了哈姆的声音。已经在半月湖上露出本色的哈姆的战斗是不可避免的，也没有必要避免。\n\n与以往不同，可以与南河争鸣。趁着哈姆暂时退缩的时候，想要一击的瞬间出现了上升，挡住了前面。一起出现的阿郎试图说服她但是行不通。阿郎成功地让阿郎在她出现漏洞的瞬间，用真名刺破了她的下肢。\n倒下的下肢再次站起来时，与以往不同，是奇洙的样子。我和阿郎拼命对抗骑手河，经过激烈的搏斗，终于倒下了。\n\n打起精神的登山，不顾大骚乱，帮助调整心态，举行天神祭礼。但是好不容易叫来的帕萨却什么都没说就回去了。阿郎虽然火冒三丈，但这是无法挽回的事情。\n接下来该怎么办…？"
    },
    "11020019": {
        "deprecated": false,
        "Dev_Desc": "2막 8장",
        "id": 11020019,
        "alias": "Contents.Quest.Desc.20019",
        "text": "天神祭礼毫无收获地结束后，阿郎为了寻找肥沃而离开，我决定暂时去一个安静的地方思考。在这样的参考森林里，一个看到人类模样的帕萨找到了我。\n\n随着帕萨的话，我走进了一个熟悉的走廊，在那里我可以听到关于母亲和父亲的故事。在那故事中，我父亲杀死了母亲。\n\n陷入冲击，从觉醒的走廊里出来后，腿放松了，犹豫了一下。那时候，不知怎么来的，阿郎出现了，伸出了手。向阿郎吐露了事实，他说：不能保证这都是事实。\n\n所以我们像半月湖一样对联，但没有出现裂痕。阿郎建立了一个没有肥沃的家庭，并说一起去拿肥沃。求肥就那么容易吗..。总之跟阿郎走吧。"
    },
    "11020020": {
        "deprecated": false,
        "Dev_Desc": "2막 9장",
        "id": 11020020,
        "alias": "Contents.Quest.Desc.20020",
        "text": "经过雾林开拓地的我们面前出现了风白门的长老飞流河。从回去的情况来看，阿郎是阿郎的死刑，阿郎是风白门的主人。你这个叛徒。在一起的时间是多少，这段时间一次都不告诉我…\n阿郎就像被非流下抓住了什么弱点一样，对他不知所措。最终，我们决定在非流下的劝导下，不得不帮助首阳。\n\n听雾林开拓地的负责人说，淡草的个体数量激增，通行困难。负责人表示：虽然想通过标本从根本上解决问题，但首阳领导层却表示不要放松。我们在据点负责人的委托下获得了草的标本。约在那里见面的飞流河留下一封信，先去了丰白门海月支部。\n让我比喻的人有点轻…！不管怎样走吧风白门。"
    },
    "11020021": {
        "deprecated": false,
        "Dev_Desc": "2막 4장",
        "id": 11020021,
        "alias": "Contents.Quest.Desc.20021",
        "text": "还没有公开的故事"
    },
    "11020022": {
        "deprecated": false,
        "Dev_Desc": "2막 5장",
        "id": 11020022,
        "alias": "Contents.Quest.Desc.20022",
        "text": "还没有公开的故事"
    },
    "11020023": {
        "deprecated": false,
        "Dev_Desc": "2막 4장",
        "id": 11020023,
        "alias": "Contents.Quest.Desc.20023",
        "text": "雾霭中传来熟悉的声音\n月光风和钢铁拳头啊？正好要把金嘤哲的剑救回来。\n月光风好像有点生气…？\n\n听两人的故事，谈谈金嘤铁剑吧。"
    },
    "11020024": {
        "deprecated": false,
        "Dev_Desc": "2막 5장",
        "id": 11020024,
        "alias": "Contents.Quest.Desc.20024",
        "text": "现在剩下的材料是照亮道路的镜子桃花镜！\n比想象中顺利地寻找祭祀材料。正好听说雾林开拓地有桃花商战主郭浩龙。"
    },
    "11020025": {
        "deprecated": false,
        "Dev_Desc": "2막 4장",
        "id": 11020025,
        "alias": "Contents.Quest.Desc.20025",
        "text": "指的是制作道路的黑色金嘤铁门的宝剑，金嘤铁剑。\n\n在雾荫下遇到的月光风和钢铁拳头正在研究通过幻影魂火冶炼钢铁的方法。钢铁拳头意外地害怕幻影，不知所措，替他处理幻影，聚集了魂火。之后，还获得了烟草的津液、枯木的皮，顺利地获得了金嘤铁剑。\n\n人的人脉还是很重要的！没想到半月湖帮了我一把。\n下面是照亮道路的镜子桃花镜！找郭浩龙谈谈情况。"
    },
    "11020026": {
        "deprecated": false,
        "Dev_Desc": "2막 5장",
        "id": 11020026,
        "alias": "Contents.Quest.Desc.20026",
        "text": "照在路上的镜子，桃花像传的桃花经不是世代相传的东西。幸运的是制作起来很简单，可以通过郭浩龙上殿主的介绍得到桃花上殿工艺家的引导。\n为了得到桃花镜的材料，在干燥的沼泽中救出了被人面虫威胁的桃花上殿的工人。然后带着黑色的沙子回到工艺家那里。修整沙子，准备柴火，帮助了工艺家，顺利地得到了桃花镜。许可证和三种材料，都收集好了，现在只剩下去埃莱达秘密据点举行天神祭礼了！"
    }
}