{
    "30010000": "Возьми мое копье ~!",
    "30010001": "Я все заблокирую щитом !!",
    "30010002": "Ваши навыки мне не подходят.",
    "30010003": "Этот человек. Ты лучший!",
    "30010004": "Это <textColor=[78:148:215:255]> мужчина </> в порядке ...?",
    "30010005": "...",
    "30010006": "Уф ...",
    "30010007": "Давайте сосредоточимся, сосредоточимся.",
    "30010008": "Я так взволнован, что все мое тело дрожит ...",
    "30010009": "Если бы я только мог получить этот <textColor=[255:204:102:255]> образец </> ...!",
    "30010010": "Хорошо! Теперь о <textColor=[255:204:102:255]> Crack </> \n Я наконец могу это понять !!",
    "30010011": "Аааа! Никто не может сравниться с этим <textColor=[78:148:215:255]> Кю-Нын Ким </> насчет трещин!",
    "30010012": "А теперь ... давайте начнем с некоторого <textColor=[255:204:102:255]> образца </> ...",
    "30010013": "Разве нет возможности ...?",
    "30010014": "Старый пират уродлив!",
    "30010015": "Хвастовство - это посланник!",
    "30010016": "Зря принес ... \n Что с тобой ...",
    "30010017": "Отзывы этого парня повсюду ...!",
    "30010018": "Где ты это видел ... \n Ах! Это просто ?!",
    "30010019": "Что мне делать с этими <textColor=[215:94:94:255]> пузырями </> ниггерами \n ...",
    "30010020": "Смотреть.",
    "30010021": "Это похоже на действительно загадочные руины ...!",
    "30010022": "Хуэн ~ Я жив!",
    "30010023": "Эй, хе! Как хорошо ... \n Земля меня пожирает ...!",
    "30010024": "Хм ... что случилось ...? \n Я ничего не могу вспомнить ...",
    "30010025": "А ... Что с этим не так ... \n Я собираюсь получить от менеджера отругание ...",
    "30010026": "Эй, я думал, что умру!",
    "30010027": "Это все потому, что это весело!",
    "30010028": "Что делать с великим Джимми Богом \n Хогу, а, нет, вербовкой членов!",
    "30010029": "Гарантированно высокое вознаграждение! \n Гарантированная пожизненная работа!",
    "30010030": "Да ладно, дело не в том, чтобы набирать \n участников каждый день.",
    "30010031": "Где ты хочешь попробовать?",
    "30010032": "Капитан, он может чем-нибудь помочь?",
    "30010033": "Милая, что ты думаешь об этом капитане? \n Он сказал, что просто пропустил бы сладкую воду и выбросил ее.",
    "30010034": "Действительно, наш капитан!",
    "30010035": "Ммммм? \n Капитан, он действительно нашел его?",
    "30010036": "Эй ... Больше, чем я думал. \n Это потрясающе, босс.",
    "30010037": "Это становится больше?",
    "30010038": "Капитан, пошли!",
    "30010039": "Черт, капитан !!",
    "30010040": "Где ты, черт возьми...",
    "30010041": "Разве не поэтому мы не можем встретиться?",
    "30010042": "С сегодняшнего дня вся деятельность будет приостановлена.",
    "30010043": "Поторопись и избавься от вещей.",
    "30010044": "Правда? Правда? \n Я так рада !!",
    "30010045": "Увидимся в порту Суволь!",
    "30010046": "Новаторство продолжается!",
    "30010047": "Я готов!",
    "30010048": "Пойдем!",
    "30010049": "Давай встретимся снова, если подойдем ближе!",
    "30010050": "До свидания!",
    "30010051": "Увидимся!",
    "30010052": "Да, это ты! Иди сюда ~",
    "30010053": "Вот оно ~!",
    "30010054": "Это то, что вы меня зовете?",
    "30010055": "Ах ~ <textColor=[78:148:215:255]> Инсамон </> Таинственные существа!",
    "30010056": "Я уверен, что когда-нибудь ... !!",
    "30010057": "Я также хочу присоединиться к <textColor=[78:148:215:255]> Бисамун </> ~",
    "30010058": "Нет! \n Драгоценный шедевр режиссера!",
    "30010059": "Как бы вы были расстроены, если бы об этом узнал менеджер ...",
    "30010060": "Ты… ты, что! \n Я же сказал тебе не подходить ближе !!!",
    "30010061": "Не подходи! Не приходи!",
    "30010062": "Хе-хе-хе, у меня тоже была ситуация ...",
    "30010063": "Все это сейчас бессмысленно, но \n Я не мог сдержать гнев ... Мне очень жаль.",
    "30010064": "Хе-хе! Ты не можешь остановить это ~?",
    "30010065": "Я потом не буду плакать, что копье сломалось!",
    "30010066": "Моя мама сказала \n, что на соревнованиях по боевым искусствам был бунт.",
    "30010067": "Это значит, что в небе дыра \n!",
    "30010068": "Эй, не лги! Как сделать дыру в небе?",
    "30010069": "Си, это правда ?!",
    "30010070": "Айгу! Это Саксин.",
    "30010071": "Эй, если ты будешь так работать, \n Мун Джу будет сильно обижен.",
    "30010072": "Ух !!! Сюрприз !!!",
    "30010073": "Эээ ...",
    "30010074": "О, где ты, черт возьми, был ...?",
    "30010075": "Это действительно потрясающе ~",
    "30010076": "Я буду здесь!",
    "30010077": "Живи, да нянь нянг !!!!",
    "30010078": "Хммм ...",
    "30010079": "Ах !!",
    "30010080": "Вы должны обращаться с этим осторожно!",
    "30010081": "Почему бы тебе не прийти ...?",
    "30010082": "Не могли бы вы поторопиться?",
    "30010083": "Вы должны сотрудничать.",
    "30010084": "Цыпленок ... \n Погодите ...",
    "30010085": "Кого вы спросили ...?",
    "30010086": "Я не могу больше этого терпеть! \n Я сделаю это по-своему.",
    "30010087": "Что ты? \n Если не можешь помочь, сойди.",
    "30010088": "Ой, Сохян ...!",
    "30010089": "... Сестра ... До свидания ...!",
    "30010090": "Ух ... Сохян ...",
    "30010091": "Что это ~ \n Ооооо!",
    "30010092": "Ух ... Я хочу вернуться.",
    "30010093": "Что это...",
    "30010094": "Этч !!!!!",
    "30010095": "Ааааа !!",
    "30010096": "Хорошо ...! \n Надеюсь, ты это сделаешь!",
    "30010097": "Кстати ... как я могу тебя спасти?",
    "30010098": "Готовься вернуть деревню!",
    "30010099": "Оружие и доспехи готовы, Сува!",
    "30010100": "Не говори так! Открой глаза и ищи это!",
    "30010101": "Это прекрасно, если у вас есть только живой экземпляр ...",
    "30010102": "Спасибо за помощь.",
    "30010103": "Основание валуна \n не так уж далеко.",
    "30010104": "Тттттт ... Что, если это правильно ...",
    "30010105": "Подожди, посмотри на меня.",
    "30010106": "<textColor=[255:204:102:255]> <myHero.name/>! Вы это видели?",
    "30010107": "Удачного путешествия!",
    "30010108": "До скорого!",
    "30010109": "Подожди немного. \n Я скоро поправлюсь",
    "30010110": "Ого ... как мы можем говорить ... \n Кажется, он сильно вырос ...",
    "30010111": "В любом случае ... \n Мне очень жаль."
}